Workbook

Sheet Dashboard
A1: Dashboard Fixed Income & Middle Office | B1: Dashboard Fixed Income & Middle Office | C1: Dashboard Fixed Income & Middle Office | D1: Dashboard Fixed Income & Middle Office | E1: Dashboard Fixed Income & Middle Office | F1: Dashboard Fixed Income & Middle Office | G1: Dashboard Fixed Income & Middle Office | H1: Dashboard Fixed Income & Middle Office | I1: Dashboard Fixed Income & Middle Office | J1: Dashboard Fixed Income & Middle Office | K1: Dashboard Fixed Income & Middle Office | L1: Dashboard Fixed Income & Middle Office | M1: Dashboard Fixed Income & Middle Office | N1: Dashboard Fixed Income & Middle Office | O1: Dashboard Fixed Income & Middle Office | P1: Dashboard Fixed Income & Middle Office
A2: Projet candidat - Gestion Obligataire & Gestion de Fortune | Sofia Kammoune | 11/08/2026 | B2: Projet candidat - Gestion Obligataire & Gestion de Fortune | Sofia Kammoune | 11/08/2026 | C2: Projet candidat - Gestion Obligataire & Gestion de Fortune | Sofia Kammoune | 11/08/2026 | D2: Projet candidat - Gestion Obligataire & Gestion de Fortune | Sofia Kammoune | 11/08/2026 | E2: Projet candidat - Gestion Obligataire & Gestion de Fortune | Sofia Kammoune | 11/08/2026 | F2: Projet candidat - Gestion Obligataire & Gestion de Fortune | Sofia Kammoune | 11/08/2026 | G2: Projet candidat - Gestion Obligataire & Gestion de Fortune | Sofia Kammoune | 11/08/2026 | H2: Projet candidat - Gestion Obligataire & Gestion de Fortune | Sofia Kammoune | 11/08/2026 | I2: Projet candidat - Gestion Obligataire & Gestion de Fortune | Sofia Kammoune | 11/08/2026 | J2: Projet candidat - Gestion Obligataire & Gestion de Fortune | Sofia Kammoune | 11/08/2026 | K2: Projet candidat - Gestion Obligataire & Gestion de Fortune | Sofia Kammoune | 11/08/2026 | L2: Projet candidat - Gestion Obligataire & Gestion de Fortune | Sofia Kammoune | 11/08/2026 | M2: Projet candidat - Gestion Obligataire & Gestion de Fortune | Sofia Kammoune | 11/08/2026 | N2: Projet candidat - Gestion Obligataire & Gestion de Fortune | Sofia Kammoune | 11/08/2026 | O2: Projet candidat - Gestion Obligataire & Gestion de Fortune | Sofia Kammoune | 11/08/2026 | P2: Projet candidat - Gestion Obligataire & Gestion de Fortune | Sofia Kammoune | 11/08/2026
A4: VALEUR DE MARCHE | B4: VALEUR DE MARCHE | C4: VALEUR DE MARCHE | D4: VALEUR DE MARCHE | E4: RENDEMENT PONDERE | F4: RENDEMENT PONDERE | G4: RENDEMENT PONDERE | H4: RENDEMENT PONDERE | I4: DURATION MODIFIEE | J4: DURATION MODIFIEE | K4: DURATION MODIFIEE | L4: DURATION MODIFIEE | M4: DV01 EUR / PB | N4: DV01 EUR / PB | O4: DV01 EUR / PB | P4: DV01 EUR / PB
A5: =Portefeuille!$K$13 -> 10227860 | E5: =SUMPRODUCT(Portefeuille!$H$5:$H$12,Portefeuille!$Q$5:$Q$12) -> 0.028908457 | I5: =Portefeuille!$M$13 -> 3.7887767 | M5: =Portefeuille!$O$13 -> 3875.1079
A9: Synthese du risque | B9: Synthese du risque | C9: Synthese du risque | D9: Synthese du risque | E9: Synthese du risque | F9: Synthese du risque | G9: Synthese du risque
A10: Indicateur | B10: Valeur | C10: Lecture
A11: Convexite ponderee | B11: =Portefeuille!$N$13 -> 24.029538 | C11: Effet de second ordre
A12: Pire scenario | B12: Hausse parallele +100 pb | C12: Stress le plus negatif
A13: PnL du pire scenario | B13: ='Stress Tests'!$B$50 -> -462850.85 | C13: Impact taux + spreads
A14: Impact relatif | B14: ='Stress Tests'!$C$50 -> -0.045253928 | C14: % de la valeur de marche
A15: Statut du modele | B15: =Checks!$B$16 -> OK | C15: Tous les controles doivent etre OK
A18: Couverture et operations | B18: Couverture et operations | C18: Couverture et operations | D18: Couverture et operations | E18: Couverture et operations | F18: Couverture et operations | G18: Couverture et operations
A19: Indicateur | B19: Valeur | C19: Statut
A20: Contrats futures | B20: =Couverture!$B$8 -> -46 | C20: Indicatif
A21: DV01 residuelle | B21: =Couverture!$B$9 -> -34.892083 | C21: Apres couverture
A22: Efficacite couverture | B22: =Couverture!$B$10 -> 0.99099584 | C22: >= 95%
A23: Appels de marge nets | B23: =SUM(Collateral!$L$5:$L$10) -> 30000 | C23: Recevoir (+) / poster (-)
A24: Exceptions collateral | B24: =Collateral!$B$17 -> 1 | C24: A investiguer
A25: Exceptions trades | B25: =COUNTIF(Reconciliation!$K$5:$K$12,"EXCEPTION") -> 2 | C25: A investiguer
A28: Point d'attention : la hausse parallele de 100 pb combinee a un leger widening produit la perte la plus forte. La couverture DV01 reduit fortement le risque de taux lineaire mais ne neutralise ni la convexite, ni le spread de credit, ni le risque de base. | B28: Point d'attention : la hausse parallele de 100 pb combinee a un leger widening produit la perte la plus forte. La couverture DV01 reduit fortement le risque de taux lineaire mais ne neutralise ni la convexite, ni le spread de credit, ni le risque de base. | C28: Point d'attention : la hausse parallele de 100 pb combinee a un leger widening produit la perte la plus forte. La couverture DV01 reduit fortement le risque de taux lineaire mais ne neutralise ni la convexite, ni le spread de credit, ni le risque de base. | D28: Point d'attention : la hausse parallele de 100 pb combinee a un leger widening produit la perte la plus forte. La couverture DV01 reduit fortement le risque de taux lineaire mais ne neutralise ni la convexite, ni le spread de credit, ni le risque de base. | E28: Point d'attention : la hausse parallele de 100 pb combinee a un leger widening produit la perte la plus forte. La couverture DV01 reduit fortement le risque de taux lineaire mais ne neutralise ni la convexite, ni le spread de credit, ni le risque de base. | F28: Point d'attention : la hausse parallele de 100 pb combinee a un leger widening produit la perte la plus forte. La couverture DV01 reduit fortement le risque de taux lineaire mais ne neutralise ni la convexite, ni le spread de credit, ni le risque de base. | G28: Point d'attention : la hausse parallele de 100 pb combinee a un leger widening produit la perte la plus forte. La couverture DV01 reduit fortement le risque de taux lineaire mais ne neutralise ni la convexite, ni le spread de credit, ni le risque de base.
A29: Point d'attention : la hausse parallele de 100 pb combinee a un leger widening produit la perte la plus forte. La couverture DV01 reduit fortement le risque de taux lineaire mais ne neutralise ni la convexite, ni le spread de credit, ni le risque de base. | B29: Point d'attention : la hausse parallele de 100 pb combinee a un leger widening produit la perte la plus forte. La couverture DV01 reduit fortement le risque de taux lineaire mais ne neutralise ni la convexite, ni le spread de credit, ni le risque de base. | C29: Point d'attention : la hausse parallele de 100 pb combinee a un leger widening produit la perte la plus forte. La couverture DV01 reduit fortement le risque de taux lineaire mais ne neutralise ni la convexite, ni le spread de credit, ni le risque de base. | D29: Point d'attention : la hausse parallele de 100 pb combinee a un leger widening produit la perte la plus forte. La couverture DV01 reduit fortement le risque de taux lineaire mais ne neutralise ni la convexite, ni le spread de credit, ni le risque de base. | E29: Point d'attention : la hausse parallele de 100 pb combinee a un leger widening produit la perte la plus forte. La couverture DV01 reduit fortement le risque de taux lineaire mais ne neutralise ni la convexite, ni le spread de credit, ni le risque de base. | F29: Point d'attention : la hausse parallele de 100 pb combinee a un leger widening produit la perte la plus forte. La couverture DV01 reduit fortement le risque de taux lineaire mais ne neutralise ni la convexite, ni le spread de credit, ni le risque de base. | G29: Point d'attention : la hausse parallele de 100 pb combinee a un leger widening produit la perte la plus forte. La couverture DV01 reduit fortement le risque de taux lineaire mais ne neutralise ni la convexite, ni le spread de credit, ni le risque de base.
A30: Point d'attention : la hausse parallele de 100 pb combinee a un leger widening produit la perte la plus forte. La couverture DV01 reduit fortement le risque de taux lineaire mais ne neutralise ni la convexite, ni le spread de credit, ni le risque de base. | B30: Point d'attention : la hausse parallele de 100 pb combinee a un leger widening produit la perte la plus forte. La couverture DV01 reduit fortement le risque de taux lineaire mais ne neutralise ni la convexite, ni le spread de credit, ni le risque de base. | C30: Point d'attention : la hausse parallele de 100 pb combinee a un leger widening produit la perte la plus forte. La couverture DV01 reduit fortement le risque de taux lineaire mais ne neutralise ni la convexite, ni le spread de credit, ni le risque de base. | D30: Point d'attention : la hausse parallele de 100 pb combinee a un leger widening produit la perte la plus forte. La couverture DV01 reduit fortement le risque de taux lineaire mais ne neutralise ni la convexite, ni le spread de credit, ni le risque de base. | E30: Point d'attention : la hausse parallele de 100 pb combinee a un leger widening produit la perte la plus forte. La couverture DV01 reduit fortement le risque de taux lineaire mais ne neutralise ni la convexite, ni le spread de credit, ni le risque de base. | F30: Point d'attention : la hausse parallele de 100 pb combinee a un leger widening produit la perte la plus forte. La couverture DV01 reduit fortement le risque de taux lineaire mais ne neutralise ni la convexite, ni le spread de credit, ni le risque de base. | G30: Point d'attention : la hausse parallele de 100 pb combinee a un leger widening produit la perte la plus forte. La couverture DV01 reduit fortement le risque de taux lineaire mais ne neutralise ni la convexite, ni le spread de credit, ni le risque de base.
A31: Point d'attention : la hausse parallele de 100 pb combinee a un leger widening produit la perte la plus forte. La couverture DV01 reduit fortement le risque de taux lineaire mais ne neutralise ni la convexite, ni le spread de credit, ni le risque de base. | B31: Point d'attention : la hausse parallele de 100 pb combinee a un leger widening produit la perte la plus forte. La couverture DV01 reduit fortement le risque de taux lineaire mais ne neutralise ni la convexite, ni le spread de credit, ni le risque de base. | C31: Point d'attention : la hausse parallele de 100 pb combinee a un leger widening produit la perte la plus forte. La couverture DV01 reduit fortement le risque de taux lineaire mais ne neutralise ni la convexite, ni le spread de credit, ni le risque de base. | D31: Point d'attention : la hausse parallele de 100 pb combinee a un leger widening produit la perte la plus forte. La couverture DV01 reduit fortement le risque de taux lineaire mais ne neutralise ni la convexite, ni le spread de credit, ni le risque de base. | E31: Point d'attention : la hausse parallele de 100 pb combinee a un leger widening produit la perte la plus forte. La couverture DV01 reduit fortement le risque de taux lineaire mais ne neutralise ni la convexite, ni le spread de credit, ni le risque de base. | F31: Point d'attention : la hausse parallele de 100 pb combinee a un leger widening produit la perte la plus forte. La couverture DV01 reduit fortement le risque de taux lineaire mais ne neutralise ni la convexite, ni le spread de credit, ni le risque de base. | G31: Point d'attention : la hausse parallele de 100 pb combinee a un leger widening produit la perte la plus forte. La couverture DV01 reduit fortement le risque de taux lineaire mais ne neutralise ni la convexite, ni le spread de credit, ni le risque de base.

Sheet Portefeuille
A1: Portefeuille obligataire - positions et sensibilites | B1: Portefeuille obligataire - positions et sensibilites | C1: Portefeuille obligataire - positions et sensibilites | D1: Portefeuille obligataire - positions et sensibilites | E1: Portefeuille obligataire - positions et sensibilites | F1: Portefeuille obligataire - positions et sensibilites | G1: Portefeuille obligataire - positions et sensibilites | H1: Portefeuille obligataire - positions et sensibilites | I1: Portefeuille obligataire - positions et sensibilites | J1: Portefeuille obligataire - positions et sensibilites | K1: Portefeuille obligataire - positions et sensibilites | L1: Portefeuille obligataire - positions et sensibilites | M1: Portefeuille obligataire - positions et sensibilites | N1: Portefeuille obligataire - positions et sensibilites | O1: Portefeuille obligataire - positions et sensibilites | P1: Portefeuille obligataire - positions et sensibilites | Q1: Portefeuille obligataire - positions et sensibilites | R1: Portefeuille obligataire - positions et sensibilites
A2: Donnees illustratives au 11/08/2026 | Coupons annuels | EUR | B2: Donnees illustratives au 11/08/2026 | Coupons annuels | EUR | C2: Donnees illustratives au 11/08/2026 | Coupons annuels | EUR | D2: Donnees illustratives au 11/08/2026 | Coupons annuels | EUR | E2: Donnees illustratives au 11/08/2026 | Coupons annuels | EUR | F2: Donnees illustratives au 11/08/2026 | Coupons annuels | EUR | G2: Donnees illustratives au 11/08/2026 | Coupons annuels | EUR | H2: Donnees illustratives au 11/08/2026 | Coupons annuels | EUR | I2: Donnees illustratives au 11/08/2026 | Coupons annuels | EUR | J2: Donnees illustratives au 11/08/2026 | Coupons annuels | EUR | K2: Donnees illustratives au 11/08/2026 | Coupons annuels | EUR | L2: Donnees illustratives au 11/08/2026 | Coupons annuels | EUR | M2: Donnees illustratives au 11/08/2026 | Coupons annuels | EUR | N2: Donnees illustratives au 11/08/2026 | Coupons annuels | EUR | O2: Donnees illustratives au 11/08/2026 | Coupons annuels | EUR | P2: Donnees illustratives au 11/08/2026 | Coupons annuels | EUR | Q2: Donnees illustratives au 11/08/2026 | Coupons annuels | EUR | R2: Donnees illustratives au 11/08/2026 | Coupons annuels | EUR
A4: ID | B4: Instrument | C4: Secteur | D4: Rating | E4: Echeance | F4: Annees | G4: Coupon | H4: YTM | I4: Nominal EUR | J4: Prix / 100 | K4: Valeur de marche | L4: Duration Macaulay | M4: Duration modifiee | N4: Convexite | O4: DV01 EUR/pb | P4: Spread pb | Q4: Poids | R4: Bucket maturite
A5: B01 | B5: Souverain EUR 2027 | C5: Souverain | D5: AAA | E5: 46610 | F5: 1 | G5: 0 | H5: 0.021 | I5: 2000000 | J5: =Cashflows!$O$6 -> 97.943193 | K5: =I5*J5/100 -> 1958863.9 | L5: =Cashflows!$P$7 -> 1 | M5: =L5/(1+H5) -> 0.97943193 | N5: =Cashflows!$P$8 -> 1.9185738 | O5: =M5*K5*0.0001 -> 191.85738 | P5: 5 | Q5: =K5/$K$13 -> 0.19152235 | R5: =IF(F5<=3,"Court <= 3 ans",IF(F5<=7,"Moyen 4-7 ans","Long > 7 ans")) -> Court <= 3 ans
A6: B02 | B6: Souverain EUR 2029 | C6: Souverain | D6: AAA | E6: 47341 | F6: 3 | G6: 0.02 | H6: 0.0225 | I6: 1800000 | J6: =Cashflows!$O$11 -> 99.282526 | K6: =I6*J6/100 -> 1787085.5 | L6: =Cashflows!$P$12 -> 2.9413298 | M6: =L6/(1+H6) -> 2.8766061 | N6: =Cashflows!$P$13 -> 11.178681 | O6: =M6*K6*0.0001 -> 514.0741 | P6: 8 | Q6: =K6/$K$13 -> 0.17472721 | R6: =IF(F6<=3,"Court <= 3 ans",IF(F6<=7,"Moyen 4-7 ans","Long > 7 ans")) -> Court <= 3 ans
A7: B03 | B7: Souverain EUR 2032 | C7: Souverain | D7: AA | E7: 48437 | F7: 6 | G7: 0.0275 | H7: 0.025 | I7: 1500000 | J7: =Cashflows!$O$16 -> 101.37703 | K7: =I7*J7/100 -> 1520655.5 | L7: =Cashflows!$P$17 -> 5.6157032 | M7: =L7/(1+H7) -> 5.4787349 | N7: =Cashflows!$P$18 -> 36.576187 | O7: =M7*K7*0.0001 -> 833.12681 | P7: 18 | Q7: =K7/$K$13 -> 0.14867777 | R7: =IF(F7<=3,"Court <= 3 ans",IF(F7<=7,"Moyen 4-7 ans","Long > 7 ans")) -> Moyen 4-7 ans
A8: B04 | B8: Corporate Utilities 2028 | C8: Corporate | D8: A | E8: 46976 | F8: 2 | G8: 0.032 | H8: 0.03 | I8: 1200000 | J8: =Cashflows!$O$21 -> 100.38269 | K8: =I8*J8/100 -> 1204592.3 | L8: =Cashflows!$P$22 -> 1.9690505 | M8: =L8/(1+H8) -> 1.9116995 | N8: =Cashflows!$P$23 -> 5.5388839 | O8: =M8*K8*0.0001 -> 230.28185 | P8: 75 | Q8: =K8/$K$13 -> 0.11777559 | R8: =IF(F8<=3,"Court <= 3 ans",IF(F8<=7,"Moyen 4-7 ans","Long > 7 ans")) -> Court <= 3 ans
A9: B05 | B9: Banque Senior 2030 | C9: Financier | D9: A | E9: 47706 | F9: 4 | G9: 0.0375 | H9: 0.034 | I9: 1000000 | J9: =Cashflows!$O$26 -> 101.28864 | K9: =I9*J9/100 -> 1012886.4 | L9: =Cashflows!$P$27 -> 3.7898376 | M9: =L9/(1+H9) -> 3.6652201 | N9: =Cashflows!$P$28 -> 17.39951 | O9: =M9*K9*0.0001 -> 371.24514 | P9: 95 | Q9: =K9/$K$13 -> 0.099032086 | R9: =IF(F9<=3,"Court <= 3 ans",IF(F9<=7,"Moyen 4-7 ans","Long > 7 ans")) -> Moyen 4-7 ans
A10: B06 | B10: Corporate Industrie 2031 | C10: Corporate | D10: BBB | E10: 48071 | F10: 5 | G10: 0.041 | H10: 0.039 | I10: 900000 | J10: =Cashflows!$O$31 -> 100.89287 | K10: =I10*J10/100 -> 908035.84 | L10: =Cashflows!$P$32 -> 4.6232896 | M10: =L10/(1+H10) -> 4.4497493 | N10: =Cashflows!$P$33 -> 25.011612 | O10: =M10*K10*0.0001 -> 404.05319 | P10: 145 | Q10: =K10/$K$13 -> 0.088780625 | R10: =IF(F10<=3,"Court <= 3 ans",IF(F10<=7,"Moyen 4-7 ans","Long > 7 ans")) -> Moyen 4-7 ans
A11: B07 | B11: Souverain EUR 2034 | C11: Souverain | D11: BBB | E11: 49167 | F11: 8 | G11: 0.04 | H11: 0.036 | I11: 1100000 | J11: =Cashflows!$O$36 -> 102.73814 | K11: =I11*J11/100 -> 1130119.6 | L11: =Cashflows!$P$37 -> 7.0177724 | M11: =L11/(1+H11) -> 6.7739116 | N11: =Cashflows!$P$38 -> 56.196614 | O11: =M11*K11*0.0001 -> 765.53301 | P11: 120 | Q11: =K11/$K$13 -> 0.11049423 | R11: =IF(F11<=3,"Court <= 3 ans",IF(F11<=7,"Moyen 4-7 ans","Long > 7 ans")) -> Long > 7 ans
A12: B08 | B12: Green Bond Corporate 2036 | C12: Corporate | D12: BBB | E12: 49898 | F12: 10 | G12: 0.043 | H12: 0.042 | I12: 700000 | J12: =Cashflows!$O$41 -> 100.80307 | K12: =I12*J12/100 -> 705621.52 | L12: =Cashflows!$P$42 -> 8.342486 | M12: =L12/(1+H12) -> 8.0062245 | N12: =Cashflows!$P$43 -> 79.220004 | O12: =M12*K12*0.0001 -> 564.93643 | P12: 175 | Q12: =K12/$K$13 -> 0.06899014 | R12: =IF(F12<=3,"Court <= 3 ans",IF(F12<=7,"Moyen 4-7 ans","Long > 7 ans")) -> Long > 7 ans
A13: TOTAL / MOYENNES PONDEREES | B13: TOTAL / MOYENNES PONDEREES | C13: TOTAL / MOYENNES PONDEREES | D13: TOTAL / MOYENNES PONDEREES | E13: TOTAL / MOYENNES PONDEREES | F13: TOTAL / MOYENNES PONDEREES | G13: TOTAL / MOYENNES PONDEREES | H13: TOTAL / MOYENNES PONDEREES | I13: TOTAL / MOYENNES PONDEREES | J13: TOTAL / MOYENNES PONDEREES | K13: =SUM(K5:K12) -> 10227860 | L13: =SUMPRODUCT(L5:L12,Q5:Q12) -> 3.9090357 | M13: =SUMPRODUCT(M5:M12,Q5:Q12) -> 3.7887767 | N13: =SUMPRODUCT(N5:N12,Q5:Q12) -> 24.029538 | O13: =SUM(O5:O12) -> 3875.1079 | Q13: =SUM(Q5:Q12) -> 1
A16: Allocation par rating | B16: Allocation par rating | C16: Allocation par rating | D16: Allocation par rating | F16: DV01 par maturite | G16: DV01 par maturite | H16: DV01 par maturite | I16: DV01 par maturite
A17: Rating | B17: Valeur de marche | F17: Bucket | G17: DV01 EUR/pb
A18: AAA | B18: =SUMIF($D$5:$D$12,A18,$K$5:$K$12) -> 3745949.3 | F18: Court <= 3 ans | G18: =SUMIF($R$5:$R$12,F18,$O$5:$O$12) -> 936.21333
A19: AA | B19: =SUMIF($D$5:$D$12,A19,$K$5:$K$12) -> 1520655.5 | F19: Moyen 4-7 ans | G19: =SUMIF($R$5:$R$12,F19,$O$5:$O$12) -> 1608.4251
A20: A | B20: =SUMIF($D$5:$D$12,A20,$K$5:$K$12) -> 2217478.7 | F20: Long > 7 ans | G20: =SUMIF($R$5:$R$12,F20,$O$5:$O$12) -> 1330.4694
A21: BBB | B21: =SUMIF($D$5:$D$12,A21,$K$5:$K$12) -> 2743776.9

Sheet Cashflows
A1: Moteur de calcul obligataire | B1: Moteur de calcul obligataire | C1: Moteur de calcul obligataire | D1: Moteur de calcul obligataire | E1: Moteur de calcul obligataire | F1: Moteur de calcul obligataire | G1: Moteur de calcul obligataire | H1: Moteur de calcul obligataire | I1: Moteur de calcul obligataire | J1: Moteur de calcul obligataire | K1: Moteur de calcul obligataire | L1: Moteur de calcul obligataire | M1: Moteur de calcul obligataire | N1: Moteur de calcul obligataire | O1: Moteur de calcul obligataire | P1: Moteur de calcul obligataire
A2: Flux annuels actualises | Formules auditables | B2: Flux annuels actualises | Formules auditables | C2: Flux annuels actualises | Formules auditables | D2: Flux annuels actualises | Formules auditables | E2: Flux annuels actualises | Formules auditables | F2: Flux annuels actualises | Formules auditables | G2: Flux annuels actualises | Formules auditables | H2: Flux annuels actualises | Formules auditables | I2: Flux annuels actualises | Formules auditables | J2: Flux annuels actualises | Formules auditables | K2: Flux annuels actualises | Formules auditables | L2: Flux annuels actualises | Formules auditables | M2: Flux annuels actualises | Formules auditables | N2: Flux annuels actualises | Formules auditables | O2: Flux annuels actualises | Formules auditables | P2: Flux annuels actualises | Formules auditables
A3: Bond ID | B3: Metrique | C3: Maturite | D3: YTM | E3: 1 | F3: 2 | G3: 3 | H3: 4 | I3: 5 | J3: 6 | K3: 7 | L3: 8 | M3: 9 | N3: 10 | O3: Total | P3: Indicateur
A5: B01 | B5: Flux | C5: 1 | D5: 0.021 | E5: =IF(E$3<=$C5,IF(E$3=$C5,Portefeuille!$G$5*100+100,Portefeuille!$G$5*100),0) -> 100 | F5: =IF(F$3<=$C5,IF(F$3=$C5,Portefeuille!$G$5*100+100,Portefeuille!$G$5*100),0) -> 0 | G5: =IF(G$3<=$C5,IF(G$3=$C5,Portefeuille!$G$5*100+100,Portefeuille!$G$5*100),0) -> 0 | H5: =IF(H$3<=$C5,IF(H$3=$C5,Portefeuille!$G$5*100+100,Portefeuille!$G$5*100),0) -> 0 | I5: =IF(I$3<=$C5,IF(I$3=$C5,Portefeuille!$G$5*100+100,Portefeuille!$G$5*100),0) -> 0 | J5: =IF(J$3<=$C5,IF(J$3=$C5,Portefeuille!$G$5*100+100,Portefeuille!$G$5*100),0) -> 0 | K5: =IF(K$3<=$C5,IF(K$3=$C5,Portefeuille!$G$5*100+100,Portefeuille!$G$5*100),0) -> 0 | L5: =IF(L$3<=$C5,IF(L$3=$C5,Portefeuille!$G$5*100+100,Portefeuille!$G$5*100),0) -> 0 | ... N5: =IF(N$3<=$C5,IF(N$3=$C5,Portefeuille!$G$5*100+100,Portefeuille!$G$5*100),0) -> 0 | O5: =SUM(E5:N5) -> 100 | P5: Flux total
A6: B01 | B6: Valeur actuelle | C6: 1 | D6: 0.021 | E6: =E5/(1+$D6)^E$3 -> 97.943193 | F6: =F5/(1+$D6)^F$3 -> 0 | G6: =G5/(1+$D6)^G$3 -> 0 | H6: =H5/(1+$D6)^H$3 -> 0 | I6: =I5/(1+$D6)^I$3 -> 0 | J6: =J5/(1+$D6)^J$3 -> 0 | K6: =K5/(1+$D6)^K$3 -> 0 | L6: =L5/(1+$D6)^L$3 -> 0 | ... N6: =N5/(1+$D6)^N$3 -> 0 | O6: =SUM(E6:N6) -> 97.943193 | P6: =O6 -> 97.943193
A7: B01 | B7: t x VA | C7: 1 | D7: 0.021 | E7: =E$3*E6 -> 97.943193 | F7: =F$3*F6 -> 0 | G7: =G$3*G6 -> 0 | H7: =H$3*H6 -> 0 | I7: =I$3*I6 -> 0 | J7: =J$3*J6 -> 0 | K7: =K$3*K6 -> 0 | L7: =L$3*L6 -> 0 | ... N7: =N$3*N6 -> 0 | O7: =SUM(E7:N7) -> 97.943193 | P7: =O7/O6 -> 1
A8: B01 | B8: t(t+1) x VA | C8: 1 | D8: 0.021 | E8: =E$3*(E$3+1)*E6 -> 195.88639 | F8: =F$3*(F$3+1)*F6 -> 0 | G8: =G$3*(G$3+1)*G6 -> 0 | H8: =H$3*(H$3+1)*H6 -> 0 | I8: =I$3*(I$3+1)*I6 -> 0 | J8: =J$3*(J$3+1)*J6 -> 0 | K8: =K$3*(K$3+1)*K6 -> 0 | L8: =L$3*(L$3+1)*L6 -> 0 | ... N8: =N$3*(N$3+1)*N6 -> 0 | O8: =SUM(E8:N8) -> 195.88639 | P8: =O8/(O6*(1+D8)^2) -> 1.9185738
A10: B02 | B10: Flux | C10: 3 | D10: 0.0225 | E10: =IF(E$3<=$C10,IF(E$3=$C10,Portefeuille!$G$6*100+100,Portefeuille!$G$6*100),0) -> 2 | F10: =IF(F$3<=$C10,IF(F$3=$C10,Portefeuille!$G$6*100+100,Portefeuille!$G$6*100),0) -> 2 | G10: =IF(G$3<=$C10,IF(G$3=$C10,Portefeuille!$G$6*100+100,Portefeuille!$G$6*100),0) -> 102 | H10: =IF(H$3<=$C10,IF(H$3=$C10,Portefeuille!$G$6*100+100,Portefeuille!$G$6*100),0) -> 0 | I10: =IF(I$3<=$C10,IF(I$3=$C10,Portefeuille!$G$6*100+100,Portefeuille!$G$6*100),0) -> 0 | J10: =IF(J$3<=$C10,IF(J$3=$C10,Portefeuille!$G$6*100+100,Portefeuille!$G$6*100),0) -> 0 | K10: =IF(K$3<=$C10,IF(K$3=$C10,Portefeuille!$G$6*100+100,Portefeuille!$G$6*100),0) -> 0 | L10: =IF(L$3<=$C10,IF(L$3=$C10,Portefeuille!$G$6*100+100,Portefeuille!$G$6*100),0) -> 0 | ... N10: =IF(N$3<=$C10,IF(N$3=$C10,Portefeuille!$G$6*100+100,Portefeuille!$G$6*100),0) -> 0 | O10: =SUM(E10:N10) -> 106 | P10: Flux total
A11: B02 | B11: Valeur actuelle | C11: 3 | D11: 0.0225 | E11: =E10/(1+$D11)^E$3 -> 1.9559902 | F11: =F10/(1+$D11)^F$3 -> 1.9129489 | G11: =G10/(1+$D11)^G$3 -> 95.413587 | H11: =H10/(1+$D11)^H$3 -> 0 | I11: =I10/(1+$D11)^I$3 -> 0 | J11: =J10/(1+$D11)^J$3 -> 0 | K11: =K10/(1+$D11)^K$3 -> 0 | L11: =L10/(1+$D11)^L$3 -> 0 | ... N11: =N10/(1+$D11)^N$3 -> 0 | O11: =SUM(E11:N11) -> 99.282526 | P11: =O11 -> 99.282526
A12: B02 | B12: t x VA | C12: 3 | D12: 0.0225 | E12: =E$3*E11 -> 1.9559902 | F12: =F$3*F11 -> 3.8258977 | G12: =G$3*G11 -> 286.24076 | H12: =H$3*H11 -> 0 | I12: =I$3*I11 -> 0 | J12: =J$3*J11 -> 0 | K12: =K$3*K11 -> 0 | L12: =L$3*L11 -> 0 | ... N12: =N$3*N11 -> 0 | O12: =SUM(E12:N12) -> 292.02265 | P12: =O12/O11 -> 2.9413298
A13: B02 | B13: t(t+1) x VA | C13: 3 | D13: 0.0225 | E13: =E$3*(E$3+1)*E11 -> 3.9119804 | F13: =F$3*(F$3+1)*F11 -> 11.477693 | G13: =G$3*(G$3+1)*G11 -> 1144.963 | H13: =H$3*(H$3+1)*H11 -> 0 | I13: =I$3*(I$3+1)*I11 -> 0 | J13: =J$3*(J$3+1)*J11 -> 0 | K13: =K$3*(K$3+1)*K11 -> 0 | L13: =L$3*(L$3+1)*L11 -> 0 | ... N13: =N$3*(N$3+1)*N11 -> 0 | O13: =SUM(E13:N13) -> 1160.3527 | P13: =O13/(O11*(1+D13)^2) -> 11.178681
A15: B03 | B15: Flux | C15: 6 | D15: 0.025 | E15: =IF(E$3<=$C15,IF(E$3=$C15,Portefeuille!$G$7*100+100,Portefeuille!$G$7*100),0) -> 2.75 | F15: =IF(F$3<=$C15,IF(F$3=$C15,Portefeuille!$G$7*100+100,Portefeuille!$G$7*100),0) -> 2.75 | G15: =IF(G$3<=$C15,IF(G$3=$C15,Portefeuille!$G$7*100+100,Portefeuille!$G$7*100),0) -> 2.75 | H15: =IF(H$3<=$C15,IF(H$3=$C15,Portefeuille!$G$7*100+100,Portefeuille!$G$7*100),0) -> 2.75 | I15: =IF(I$3<=$C15,IF(I$3=$C15,Portefeuille!$G$7*100+100,Portefeuille!$G$7*100),0) -> 2.75 | J15: =IF(J$3<=$C15,IF(J$3=$C15,Portefeuille!$G$7*100+100,Portefeuille!$G$7*100),0) -> 102.75 | K15: =IF(K$3<=$C15,IF(K$3=$C15,Portefeuille!$G$7*100+100,Portefeuille!$G$7*100),0) -> 0 | L15: =IF(L$3<=$C15,IF(L$3=$C15,Portefeuille!$G$7*100+100,Portefeuille!$G$7*100),0) -> 0 | ... N15: =IF(N$3<=$C15,IF(N$3=$C15,Portefeuille!$G$7*100+100,Portefeuille!$G$7*100),0) -> 0 | O15: =SUM(E15:N15) -> 116.5 | P15: Flux total
A16: B03 | B16: Valeur actuelle | C16: 6 | D16: 0.025 | E16: =E15/(1+$D16)^E$3 -> 2.6829268 | F16: =F15/(1+$D16)^F$3 -> 2.6174896 | G16: =G15/(1+$D16)^G$3 -> 2.5536484 | H16: =H15/(1+$D16)^H$3 -> 2.4913643 | I16: =I15/(1+$D16)^I$3 -> 2.4305993 | J16: =J15/(1+$D16)^J$3 -> 88.601003 | K16: =K15/(1+$D16)^K$3 -> 0 | L16: =L15/(1+$D16)^L$3 -> 0 | ... N16: =N15/(1+$D16)^N$3 -> 0 | O16: =SUM(E16:N16) -> 101.37703 | P16: =O16 -> 101.37703
A17: B03 | B17: t x VA | C17: 6 | D17: 0.025 | E17: =E$3*E16 -> 2.6829268 | F17: =F$3*F16 -> 5.2349792 | G17: =G$3*G16 -> 7.6609451 | H17: =H$3*H16 -> 9.9654571 | I17: =I$3*I16 -> 12.152996 | J17: =J$3*J16 -> 531.60602 | K17: =K$3*K16 -> 0 | L17: =L$3*L16 -> 0 | ... N17: =N$3*N16 -> 0 | O17: =SUM(E17:N17) -> 569.30332 | P17: =O17/O16 -> 5.6157032
A18: B03 | B18: t(t+1) x VA | C18: 6 | D18: 0.025 | E18: =E$3*(E$3+1)*E16 -> 5.3658537 | F18: =F$3*(F$3+1)*F16 -> 15.704938 | G18: =G$3*(G$3+1)*G16 -> 30.643781 | H18: =H$3*(H$3+1)*H16 -> 49.827285 | I18: =I$3*(I$3+1)*I16 -> 72.917979 | J18: =J$3*(J$3+1)*J16 -> 3721.2421 | K18: =K$3*(K$3+1)*K16 -> 0 | L18: =L$3*(L$3+1)*L16 -> 0 | ... N18: =N$3*(N$3+1)*N16 -> 0 | O18: =SUM(E18:N18) -> 3895.702 | P18: =O18/(O16*(1+D18)^2) -> 36.576187
A20: B04 | B20: Flux | C20: 2 | D20: 0.03 | E20: =IF(E$3<=$C20,IF(E$3=$C20,Portefeuille!$G$8*100+100,Portefeuille!$G$8*100),0) -> 3.2 | F20: =IF(F$3<=$C20,IF(F$3=$C20,Portefeuille!$G$8*100+100,Portefeuille!$G$8*100),0) -> 103.2 | G20: =IF(G$3<=$C20,IF(G$3=$C20,Portefeuille!$G$8*100+100,Portefeuille!$G$8*100),0) -> 0 | H20: =IF(H$3<=$C20,IF(H$3=$C20,Portefeuille!$G$8*100+100,Portefeuille!$G$8*100),0) -> 0 | I20: =IF(I$3<=$C20,IF(I$3=$C20,Portefeuille!$G$8*100+100,Portefeuille!$G$8*100),0) -> 0 | J20: =IF(J$3<=$C20,IF(J$3=$C20,Portefeuille!$G$8*100+100,Portefeuille!$G$8*100),0) -> 0 | K20: =IF(K$3<=$C20,IF(K$3=$C20,Portefeuille!$G$8*100+100,Portefeuille!$G$8*100),0) -> 0 | L20: =IF(L$3<=$C20,IF(L$3=$C20,Portefeuille!$G$8*100+100,Portefeuille!$G$8*100),0) -> 0 | ... N20: =IF(N$3<=$C20,IF(N$3=$C20,Portefeuille!$G$8*100+100,Portefeuille!$G$8*100),0) -> 0 | O20: =SUM(E20:N20) -> 106.4 | P20: Flux total
A21: B04 | B21: Valeur actuelle | C21: 2 | D21: 0.03 | E21: =E20/(1+$D21)^E$3 -> 3.1067961 | F21: =F20/(1+$D21)^F$3 -> 97.275898 | G21: =G20/(1+$D21)^G$3 -> 0 | H21: =H20/(1+$D21)^H$3 -> 0 | I21: =I20/(1+$D21)^I$3 -> 0 | J21: =J20/(1+$D21)^J$3 -> 0 | K21: =K20/(1+$D21)^K$3 -> 0 | L21: =L20/(1+$D21)^L$3 -> 0 | ... N21: =N20/(1+$D21)^N$3 -> 0 | O21: =SUM(E21:N21) -> 100.38269 | P21: =O21 -> 100.38269
A22: B04 | B22: t x VA | C22: 2 | D22: 0.03 | E22: =E$3*E21 -> 3.1067961 | F22: =F$3*F21 -> 194.5518 | G22: =G$3*G21 -> 0 | H22: =H$3*H21 -> 0 | I22: =I$3*I21 -> 0 | J22: =J$3*J21 -> 0 | K22: =K$3*K21 -> 0 | L22: =L$3*L21 -> 0 | ... N22: =N$3*N21 -> 0 | O22: =SUM(E22:N22) -> 197.65859 | P22: =O22/O21 -> 1.9690505
A23: B04 | B23: t(t+1) x VA | C23: 2 | D23: 0.03 | E23: =E$3*(E$3+1)*E21 -> 6.2135922 | F23: =F$3*(F$3+1)*F21 -> 583.65539 | G23: =G$3*(G$3+1)*G21 -> 0 | H23: =H$3*(H$3+1)*H21 -> 0 | I23: =I$3*(I$3+1)*I21 -> 0 | J23: =J$3*(J$3+1)*J21 -> 0 | K23: =K$3*(K$3+1)*K21 -> 0 | L23: =L$3*(L$3+1)*L21 -> 0 | ... N23: =N$3*(N$3+1)*N21 -> 0 | O23: =SUM(E23:N23) -> 589.86898 | P23: =O23/(O21*(1+D23)^2) -> 5.5388839
A25: B05 | B25: Flux | C25: 4 | D25: 0.034 | E25: =IF(E$3<=$C25,IF(E$3=$C25,Portefeuille!$G$9*100+100,Portefeuille!$G$9*100),0) -> 3.75 | F25: =IF(F$3<=$C25,IF(F$3=$C25,Portefeuille!$G$9*100+100,Portefeuille!$G$9*100),0) -> 3.75 | G25: =IF(G$3<=$C25,IF(G$3=$C25,Portefeuille!$G$9*100+100,Portefeuille!$G$9*100),0) -> 3.75 | H25: =IF(H$3<=$C25,IF(H$3=$C25,Portefeuille!$G$9*100+100,Portefeuille!$G$9*100),0) -> 103.75 | I25: =IF(I$3<=$C25,IF(I$3=$C25,Portefeuille!$G$9*100+100,Portefeuille!$G$9*100),0) -> 0 | J25: =IF(J$3<=$C25,IF(J$3=$C25,Portefeuille!$G$9*100+100,Portefeuille!$G$9*100),0) -> 0 | K25: =IF(K$3<=$C25,IF(K$3=$C25,Portefeuille!$G$9*100+100,Portefeuille!$G$9*100),0) -> 0 | L25: =IF(L$3<=$C25,IF(L$3=$C25,Portefeuille!$G$9*100+100,Portefeuille!$G$9*100),0) -> 0 | ... N25: =IF(N$3<=$C25,IF(N$3=$C25,Portefeuille!$G$9*100+100,Portefeuille!$G$9*100),0) -> 0 | O25: =SUM(E25:N25) -> 115 | P25: Flux total
A26: B05 | B26: Valeur actuelle | C26: 4 | D26: 0.034 | E26: =E25/(1+$D26)^E$3 -> 3.6266925 | F26: =F25/(1+$D26)^F$3 -> 3.5074395 | G26: =G25/(1+$D26)^G$3 -> 3.3921078 | H26: =H25/(1+$D26)^H$3 -> 90.762396 | I26: =I25/(1+$D26)^I$3 -> 0 | J26: =J25/(1+$D26)^J$3 -> 0 | K26: =K25/(1+$D26)^K$3 -> 0 | L26: =L25/(1+$D26)^L$3 -> 0 | ... N26: =N25/(1+$D26)^N$3 -> 0 | O26: =SUM(E26:N26) -> 101.28864 | P26: =O26 -> 101.28864
A27: B05 | B27: t x VA | C27: 4 | D27: 0.034 | E27: =E$3*E26 -> 3.6266925 | F27: =F$3*F26 -> 7.014879 | G27: =G$3*G26 -> 10.176324 | H27: =H$3*H26 -> 363.04958 | I27: =I$3*I26 -> 0 | J27: =J$3*J26 -> 0 | K27: =K$3*K26 -> 0 | L27: =L$3*L26 -> 0 | ... N27: =N$3*N26 -> 0 | O27: =SUM(E27:N27) -> 383.86748 | P27: =O27/O26 -> 3.7898376
A28: B05 | B28: t(t+1) x VA | C28: 4 | D28: 0.034 | E28: =E$3*(E$3+1)*E26 -> 7.2533849 | F28: =F$3*(F$3+1)*F26 -> 21.044637 | G28: =G$3*(G$3+1)*G26 -> 40.705294 | H28: =H$3*(H$3+1)*H26 -> 1815.2479 | I28: =I$3*(I$3+1)*I26 -> 0 | J28: =J$3*(J$3+1)*J26 -> 0 | K28: =K$3*(K$3+1)*K26 -> 0 | L28: =L$3*(L$3+1)*L26 -> 0 | ... N28: =N$3*(N$3+1)*N26 -> 0 | O28: =SUM(E28:N28) -> 1884.2512 | P28: =O28/(O26*(1+D28)^2) -> 17.39951
A30: B06 | B30: Flux | C30: 5 | D30: 0.039 | E30: =IF(E$3<=$C30,IF(E$3=$C30,Portefeuille!$G$10*100+100,Portefeuille!$G$10*100),0) -> 4.1 | F30: =IF(F$3<=$C30,IF(F$3=$C30,Portefeuille!$G$10*100+100,Portefeuille!$G$10*100),0) -> 4.1 | G30: =IF(G$3<=$C30,IF(G$3=$C30,Portefeuille!$G$10*100+100,Portefeuille!$G$10*100),0) -> 4.1 | H30: =IF(H$3<=$C30,IF(H$3=$C30,Portefeuille!$G$10*100+100,Portefeuille!$G$10*100),0) -> 4.1 | I30: =IF(I$3<=$C30,IF(I$3=$C30,Portefeuille!$G$10*100+100,Portefeuille!$G$10*100),0) -> 104.1 | J30: =IF(J$3<=$C30,IF(J$3=$C30,Portefeuille!$G$10*100+100,Portefeuille!$G$10*100),0) -> 0 | K30: =IF(K$3<=$C30,IF(K$3=$C30,Portefeuille!$G$10*100+100,Portefeuille!$G$10*100),0) -> 0 | L30: =IF(L$3<=$C30,IF(L$3=$C30,Portefeuille!$G$10*100+100,Portefeuille!$G$10*100),0) -> 0 | ... N30: =IF(N$3<=$C30,IF(N$3=$C30,Portefeuille!$G$10*100+100,Portefeuille!$G$10*100),0) -> 0 | O30: =SUM(E30:N30) -> 120.5 | P30: Flux total
A31: B06 | B31: Valeur actuelle | C31: 5 | D31: 0.039 | E31: =E30/(1+$D31)^E$3 -> 3.946102 | F31: =F30/(1+$D31)^F$3 -> 3.7979808 | G31: =G30/(1+$D31)^G$3 -> 3.6554194 | H31: =H30/(1+$D31)^H$3 -> 3.5182093 | I31: =I30/(1+$D31)^I$3 -> 85.97516 | J31: =J30/(1+$D31)^J$3 -> 0 | K31: =K30/(1+$D31)^K$3 -> 0 | L31: =L30/(1+$D31)^L$3 -> 0 | ... N31: =N30/(1+$D31)^N$3 -> 0 | O31: =SUM(E31:N31) -> 100.89287 | P31: =O31 -> 100.89287
A32: B06 | B32: t x VA | C32: 5 | D32: 0.039 | E32: =E$3*E31 -> 3.946102 | F32: =F$3*F31 -> 7.5959615 | G32: =G$3*G31 -> 10.966258 | H32: =H$3*H31 -> 14.072837 | I32: =I$3*I31 -> 429.8758 | J32: =J$3*J31 -> 0 | K32: =K$3*K31 -> 0 | L32: =L$3*L31 -> 0 | ... N32: =N$3*N31 -> 0 | O32: =SUM(E32:N32) -> 466.45696 | P32: =O32/O31 -> 4.6232896
A33: B06 | B33: t(t+1) x VA | C33: 5 | D33: 0.039 | E33: =E$3*(E$3+1)*E31 -> 7.892204 | F33: =F$3*(F$3+1)*F31 -> 22.787885 | G33: =G$3*(G$3+1)*G31 -> 43.865033 | H33: =H$3*(H$3+1)*H31 -> 70.364185 | I33: =I$3*(I$3+1)*I31 -> 2579.2548 | J33: =J$3*(J$3+1)*J31 -> 0 | K33: =K$3*(K$3+1)*K31 -> 0 | L33: =L$3*(L$3+1)*L31 -> 0 | ... N33: =N$3*(N$3+1)*N31 -> 0 | O33: =SUM(E33:N33) -> 2724.1641 | P33: =O33/(O31*(1+D33)^2) -> 25.011612
A35: B07 | B35: Flux | C35: 8 | D35: 0.036 | E35: =IF(E$3<=$C35,IF(E$3=$C35,Portefeuille!$G$11*100+100,Portefeuille!$G$11*100),0) -> 4 | F35: =IF(F$3<=$C35,IF(F$3=$C35,Portefeuille!$G$11*100+100,Portefeuille!$G$11*100),0) -> 4 | G35: =IF(G$3<=$C35,IF(G$3=$C35,Portefeuille!$G$11*100+100,Portefeuille!$G$11*100),0) -> 4 | H35: =IF(H$3<=$C35,IF(H$3=$C35,Portefeuille!$G$11*100+100,Portefeuille!$G$11*100),0) -> 4 | I35: =IF(I$3<=$C35,IF(I$3=$C35,Portefeuille!$G$11*100+100,Portefeuille!$G$11*100),0) -> 4 | J35: =IF(J$3<=$C35,IF(J$3=$C35,Portefeuille!$G$11*100+100,Portefeuille!$G$11*100),0) -> 4 | K35: =IF(K$3<=$C35,IF(K$3=$C35,Portefeuille!$G$11*100+100,Portefeuille!$G$11*100),0) -> 4 | L35: =IF(L$3<=$C35,IF(L$3=$C35,Portefeuille!$G$11*100+100,Portefeuille!$G$11*100),0) -> 104 | ... N35: =IF(N$3<=$C35,IF(N$3=$C35,Portefeuille!$G$11*100+100,Portefeuille!$G$11*100),0) -> 0 | O35: =SUM(E35:N35) -> 132 | P35: Flux total
A36: B07 | B36: Valeur actuelle | C36: 8 | D36: 0.036 | E36: =E35/(1+$D36)^E$3 -> 3.8610039 | F36: =F35/(1+$D36)^F$3 -> 3.7268377 | G36: =G35/(1+$D36)^G$3 -> 3.5973337 | H36: =H35/(1+$D36)^H$3 -> 3.4723298 | I36: =I35/(1+$D36)^I$3 -> 3.3516697 | J36: =J35/(1+$D36)^J$3 -> 3.2352024 | K36: =K35/(1+$D36)^K$3 -> 3.1227823 | L36: =L35/(1+$D36)^L$3 -> 78.370983 | ... N36: =N35/(1+$D36)^N$3 -> 0 | O36: =SUM(E36:N36) -> 102.73814 | P36: =O36 -> 102.73814
A37: B07 | B37: t x VA | C37: 8 | D37: 0.036 | E37: =E$3*E36 -> 3.8610039 | F37: =F$3*F36 -> 7.4536754 | G37: =G$3*G36 -> 10.792001 | H37: =H$3*H36 -> 13.889319 | I37: =I$3*I36 -> 16.758349 | J37: =J$3*J36 -> 19.411215 | K37: =K$3*K36 -> 21.859476 | L37: =L$3*L36 -> 626.96787 | ... N37: =N$3*N36 -> 0 | O37: =SUM(E37:N37) -> 720.99291 | P37: =O37/O36 -> 7.0177724
A38: B07 | B38: t(t+1) x VA | C38: 8 | D38: 0.036 | E38: =E$3*(E$3+1)*E36 -> 7.7220077 | F38: =F$3*(F$3+1)*F36 -> 22.361026 | G38: =G$3*(G$3+1)*G36 -> 43.168004 | H38: =H$3*(H$3+1)*H36 -> 69.446596 | I38: =I$3*(I$3+1)*I36 -> 100.55009 | J38: =J$3*(J$3+1)*J36 -> 135.8785 | K38: =K$3*(K$3+1)*K36 -> 174.87581 | L38: =L$3*(L$3+1)*L36 -> 5642.7108 | ... N38: =N$3*(N$3+1)*N36 -> 0 | O38: =SUM(E38:N38) -> 6196.7128 | P38: =O38/(O36*(1+D38)^2) -> 56.196614
A40: B08 | B40: Flux | C40: 10 | D40: 0.042 | E40: =IF(E$3<=$C40,IF(E$3=$C40,Portefeuille!$G$12*100+100,Portefeuille!$G$12*100),0) -> 4.3 | F40: =IF(F$3<=$C40,IF(F$3=$C40,Portefeuille!$G$12*100+100,Portefeuille!$G$12*100),0) -> 4.3 | G40: =IF(G$3<=$C40,IF(G$3=$C40,Portefeuille!$G$12*100+100,Portefeuille!$G$12*100),0) -> 4.3 | H40: =IF(H$3<=$C40,IF(H$3=$C40,Portefeuille!$G$12*100+100,Portefeuille!$G$12*100),0) -> 4.3 | I40: =IF(I$3<=$C40,IF(I$3=$C40,Portefeuille!$G$12*100+100,Portefeuille!$G$12*100),0) -> 4.3 | J40: =IF(J$3<=$C40,IF(J$3=$C40,Portefeuille!$G$12*100+100,Portefeuille!$G$12*100),0) -> 4.3 | K40: =IF(K$3<=$C40,IF(K$3=$C40,Portefeuille!$G$12*100+100,Portefeuille!$G$12*100),0) -> 4.3 | L40: =IF(L$3<=$C40,IF(L$3=$C40,Portefeuille!$G$12*100+100,Portefeuille!$G$12*100),0) -> 4.3 | ... N40: =IF(N$3<=$C40,IF(N$3=$C40,Portefeuille!$G$12*100+100,Portefeuille!$G$12*100),0) -> 104.3 | O40: =SUM(E40:N40) -> 143 | P40: Flux total
A41: B08 | B41: Valeur actuelle | C41: 10 | D41: 0.042 | E41: =E40/(1+$D41)^E$3 -> 4.1266795 | F41: =F40/(1+$D41)^F$3 -> 3.960345 | G41: =G40/(1+$D41)^G$3 -> 3.8007149 | H41: =H40/(1+$D41)^H$3 -> 3.6475191 | I41: =I40/(1+$D41)^I$3 -> 3.5004982 | J41: =J40/(1+$D41)^J$3 -> 3.3594033 | K41: =K40/(1+$D41)^K$3 -> 3.2239955 | L41: =L40/(1+$D41)^L$3 -> 3.0940456 | ... N41: =N40/(1+$D41)^N$3 -> 69.120539 | O41: =SUM(E41:N41) -> 100.80307 | P41: =O41 -> 100.80307
A42: B08 | B42: t x VA | C42: 10 | D42: 0.042 | E42: =E$3*E41 -> 4.1266795 | F42: =F$3*F41 -> 7.9206899 | G42: =G$3*G41 -> 11.402145 | H42: =H$3*H41 -> 14.590077 | I42: =I$3*I41 -> 17.502491 | J42: =J$3*J41 -> 20.15642 | K42: =K$3*K41 -> 22.567968 | L42: =L$3*L41 -> 24.752364 | ... N42: =N$3*N41 -> 691.20539 | O42: =SUM(E42:N42) -> 840.94823 | P42: =O42/O41 -> 8.342486
A43: B08 | B43: t(t+1) x VA | C43: 10 | D43: 0.042 | E43: =E$3*(E$3+1)*E41 -> 8.2533589 | F43: =F$3*(F$3+1)*F41 -> 23.76207 | G43: =G$3*(G$3+1)*G41 -> 45.608579 | H43: =H$3*(H$3+1)*H41 -> 72.950383 | I43: =I$3*(I$3+1)*I41 -> 105.01495 | J43: =J$3*(J$3+1)*J41 -> 141.09494 | K43: =K$3*(K$3+1)*K41 -> 180.54375 | L43: =L$3*(L$3+1)*L41 -> 222.77128 | ... N43: =N$3*(N$3+1)*N41 -> 7603.2593 | O43: =SUM(E43:N43) -> 8670.4987 | P43: =O43/(O41*(1+D43)^2) -> 79.220004

Sheet Courbe Scenarios
A1: Courbe de taux et hypotheses de stress | B1: Courbe de taux et hypotheses de stress | C1: Courbe de taux et hypotheses de stress | D1: Courbe de taux et hypotheses de stress | E1: Courbe de taux et hypotheses de stress | F1: Courbe de taux et hypotheses de stress | G1: Courbe de taux et hypotheses de stress | H1: Courbe de taux et hypotheses de stress | I1: Courbe de taux et hypotheses de stress | J1: Courbe de taux et hypotheses de stress | K1: Courbe de taux et hypotheses de stress | L1: Courbe de taux et hypotheses de stress | M1: Courbe de taux et hypotheses de stress
A2: Courbe indicative - a remplacer par des donnees de marche datees | B2: Courbe indicative - a remplacer par des donnees de marche datees | C2: Courbe indicative - a remplacer par des donnees de marche datees | D2: Courbe indicative - a remplacer par des donnees de marche datees | E2: Courbe indicative - a remplacer par des donnees de marche datees | F2: Courbe indicative - a remplacer par des donnees de marche datees | G2: Courbe indicative - a remplacer par des donnees de marche datees | H2: Courbe indicative - a remplacer par des donnees de marche datees | I2: Courbe indicative - a remplacer par des donnees de marche datees | J2: Courbe indicative - a remplacer par des donnees de marche datees | K2: Courbe indicative - a remplacer par des donnees de marche datees | L2: Courbe indicative - a remplacer par des donnees de marche datees | M2: Courbe indicative - a remplacer par des donnees de marche datees
A4: Courbe spot EUR illustrative | B4: Courbe spot EUR illustrative | C4: Courbe spot EUR illustrative | E4: Matrice de scenarios (points de base) | F4: Matrice de scenarios (points de base) | G4: Matrice de scenarios (points de base) | H4: Matrice de scenarios (points de base) | I4: Matrice de scenarios (points de base) | J4: Matrice de scenarios (points de base) | K4: Matrice de scenarios (points de base) | L4: Matrice de scenarios (points de base) | M4: Matrice de scenarios (points de base)
A5: Maturite | B5: Taux spot | C5: Source | E5: Scenario | F5: Court <=3 | G5: Moyen 4-7 | H5: Long >7 | I5: AAA | J5: AA | K5: A | L5: BBB | M5: Lecture
A6: 1 | B6: 0.02 | C6: Illustratif | E6: Base | F6: 0 | G6: 0 | H6: 0 | I6: 0 | J6: 0 | K6: 0 | L6: 0 | M6: Valorisation sans choc
A7: 2 | B7: 0.021 | C7: Illustratif | E7: Hausse parallele +100 pb | F7: 100 | G7: 100 | H7: 100 | I7: 10 | J7: 15 | K7: 25 | L7: 35 | M7: Choc de taux + leger widening
A8: 3 | B8: 0.0218 | C8: Illustratif | E8: Rally taux -75 pb | F8: -75 | G8: -75 | H8: -75 | I8: -5 | J8: -8 | K8: -10 | L8: -10 | M8: Baisse des taux et resserrement
A9: 5 | B9: 0.0235 | C9: Illustratif | E9: Ecartement credit | F9: 0 | G9: 0 | H9: 0 | I9: 20 | J9: 35 | K9: 75 | L9: 150 | M9: Stress de spreads par rating
A10: 7 | B10: 0.025 | C10: Illustratif | E10: Bear steepener | F10: 25 | G10: 75 | H10: 125 | I10: 10 | J10: 15 | K10: 25 | L10: 50 | M10: Hausse plus forte sur le long terme
A11: 10 | B11: 0.0265 | C11: Illustratif
A12: 15 | B12: 0.0282 | C12: Illustratif
A13: 30 | B13: 0.0305 | C13: Illustratif

Sheet Stress Tests
A1: Stress tests taux et credit | B1: Stress tests taux et credit | C1: Stress tests taux et credit | D1: Stress tests taux et credit | E1: Stress tests taux et credit | F1: Stress tests taux et credit | G1: Stress tests taux et credit | H1: Stress tests taux et credit | I1: Stress tests taux et credit | J1: Stress tests taux et credit | K1: Stress tests taux et credit | L1: Stress tests taux et credit
A2: Approximation duration-convexite : P&L = VM x [-Dmod x choc + 0,5 x Convexite x choc^2] | B2: Approximation duration-convexite : P&L = VM x [-Dmod x choc + 0,5 x Convexite x choc^2] | C2: Approximation duration-convexite : P&L = VM x [-Dmod x choc + 0,5 x Convexite x choc^2] | D2: Approximation duration-convexite : P&L = VM x [-Dmod x choc + 0,5 x Convexite x choc^2] | E2: Approximation duration-convexite : P&L = VM x [-Dmod x choc + 0,5 x Convexite x choc^2] | F2: Approximation duration-convexite : P&L = VM x [-Dmod x choc + 0,5 x Convexite x choc^2] | G2: Approximation duration-convexite : P&L = VM x [-Dmod x choc + 0,5 x Convexite x choc^2] | H2: Approximation duration-convexite : P&L = VM x [-Dmod x choc + 0,5 x Convexite x choc^2] | I2: Approximation duration-convexite : P&L = VM x [-Dmod x choc + 0,5 x Convexite x choc^2] | J2: Approximation duration-convexite : P&L = VM x [-Dmod x choc + 0,5 x Convexite x choc^2] | K2: Approximation duration-convexite : P&L = VM x [-Dmod x choc + 0,5 x Convexite x choc^2] | L2: Approximation duration-convexite : P&L = VM x [-Dmod x choc + 0,5 x Convexite x choc^2]
A4: Scenario | B4: Bond ID | C4: Rating | D4: Annees | E4: Valeur de marche | F4: Duration mod. | G4: Convexite | H4: Choc taux pb | I4: Choc spread pb | J4: Choc total | K4: PnL EUR | L4: Valeur stressee
A5: Base | B5: B01 | C5: AAA | D5: 1 | E5: =Portefeuille!$K$5 -> 1958863.9 | F5: =Portefeuille!$M$5 -> 0.97943193 | G5: =Portefeuille!$N$5 -> 1.9185738 | H5: =IF(D5<=3,'Courbe Scenarios'!$F$6,IF(D5<=7,'Courbe Scenarios'!$G$6,'Courbe Scenarios'!$H$6)) -> 0 | I5: =IF(C5="AAA",'Courbe Scenarios'!$I$6,IF(C5="AA",'Courbe Scenarios'!$J$6,IF(C5="A",'Courbe Scenarios'!$K$6,'Courbe Scenarios'!$L$6))) -> 0 | J5: =(H5+I5)/10000 -> 0 | K5: =E5*(-F5*J5+0.5*G5*J5^2) -> 0 | L5: =E5+K5 -> 1958863.9
A6: Base | B6: B02 | C6: AAA | D6: 3 | E6: =Portefeuille!$K$6 -> 1787085.5 | F6: =Portefeuille!$M$6 -> 2.8766061 | G6: =Portefeuille!$N$6 -> 11.178681 | H6: =IF(D6<=3,'Courbe Scenarios'!$F$6,IF(D6<=7,'Courbe Scenarios'!$G$6,'Courbe Scenarios'!$H$6)) -> 0 | I6: =IF(C6="AAA",'Courbe Scenarios'!$I$6,IF(C6="AA",'Courbe Scenarios'!$J$6,IF(C6="A",'Courbe Scenarios'!$K$6,'Courbe Scenarios'!$L$6))) -> 0 | J6: =(H6+I6)/10000 -> 0 | K6: =E6*(-F6*J6+0.5*G6*J6^2) -> 0 | L6: =E6+K6 -> 1787085.5
A7: Base | B7: B03 | C7: AA | D7: 6 | E7: =Portefeuille!$K$7 -> 1520655.5 | F7: =Portefeuille!$M$7 -> 5.4787349 | G7: =Portefeuille!$N$7 -> 36.576187 | H7: =IF(D7<=3,'Courbe Scenarios'!$F$6,IF(D7<=7,'Courbe Scenarios'!$G$6,'Courbe Scenarios'!$H$6)) -> 0 | I7: =IF(C7="AAA",'Courbe Scenarios'!$I$6,IF(C7="AA",'Courbe Scenarios'!$J$6,IF(C7="A",'Courbe Scenarios'!$K$6,'Courbe Scenarios'!$L$6))) -> 0 | J7: =(H7+I7)/10000 -> 0 | K7: =E7*(-F7*J7+0.5*G7*J7^2) -> 0 | L7: =E7+K7 -> 1520655.5
A8: Base | B8: B04 | C8: A | D8: 2 | E8: =Portefeuille!$K$8 -> 1204592.3 | F8: =Portefeuille!$M$8 -> 1.9116995 | G8: =Portefeuille!$N$8 -> 5.5388839 | H8: =IF(D8<=3,'Courbe Scenarios'!$F$6,IF(D8<=7,'Courbe Scenarios'!$G$6,'Courbe Scenarios'!$H$6)) -> 0 | I8: =IF(C8="AAA",'Courbe Scenarios'!$I$6,IF(C8="AA",'Courbe Scenarios'!$J$6,IF(C8="A",'Courbe Scenarios'!$K$6,'Courbe Scenarios'!$L$6))) -> 0 | J8: =(H8+I8)/10000 -> 0 | K8: =E8*(-F8*J8+0.5*G8*J8^2) -> 0 | L8: =E8+K8 -> 1204592.3
A9: Base | B9: B05 | C9: A | D9: 4 | E9: =Portefeuille!$K$9 -> 1012886.4 | F9: =Portefeuille!$M$9 -> 3.6652201 | G9: =Portefeuille!$N$9 -> 17.39951 | H9: =IF(D9<=3,'Courbe Scenarios'!$F$6,IF(D9<=7,'Courbe Scenarios'!$G$6,'Courbe Scenarios'!$H$6)) -> 0 | I9: =IF(C9="AAA",'Courbe Scenarios'!$I$6,IF(C9="AA",'Courbe Scenarios'!$J$6,IF(C9="A",'Courbe Scenarios'!$K$6,'Courbe Scenarios'!$L$6))) -> 0 | J9: =(H9+I9)/10000 -> 0 | K9: =E9*(-F9*J9+0.5*G9*J9^2) -> 0 | L9: =E9+K9 -> 1012886.4
A10: Base | B10: B06 | C10: BBB | D10: 5 | E10: =Portefeuille!$K$10 -> 908035.84 | F10: =Portefeuille!$M$10 -> 4.4497493 | G10: =Portefeuille!$N$10 -> 25.011612 | H10: =IF(D10<=3,'Courbe Scenarios'!$F$6,IF(D10<=7,'Courbe Scenarios'!$G$6,'Courbe Scenarios'!$H$6)) -> 0 | I10: =IF(C10="AAA",'Courbe Scenarios'!$I$6,IF(C10="AA",'Courbe Scenarios'!$J$6,IF(C10="A",'Courbe Scenarios'!$K$6,'Courbe Scenarios'!$L$6))) -> 0 | J10: =(H10+I10)/10000 -> 0 | K10: =E10*(-F10*J10+0.5*G10*J10^2) -> 0 | L10: =E10+K10 -> 908035.84
A11: Base | B11: B07 | C11: BBB | D11: 8 | E11: =Portefeuille!$K$11 -> 1130119.6 | F11: =Portefeuille!$M$11 -> 6.7739116 | G11: =Portefeuille!$N$11 -> 56.196614 | H11: =IF(D11<=3,'Courbe Scenarios'!$F$6,IF(D11<=7,'Courbe Scenarios'!$G$6,'Courbe Scenarios'!$H$6)) -> 0 | I11: =IF(C11="AAA",'Courbe Scenarios'!$I$6,IF(C11="AA",'Courbe Scenarios'!$J$6,IF(C11="A",'Courbe Scenarios'!$K$6,'Courbe Scenarios'!$L$6))) -> 0 | J11: =(H11+I11)/10000 -> 0 | K11: =E11*(-F11*J11+0.5*G11*J11^2) -> 0 | L11: =E11+K11 -> 1130119.6
A12: Base | B12: B08 | C12: BBB | D12: 10 | E12: =Portefeuille!$K$12 -> 705621.52 | F12: =Portefeuille!$M$12 -> 8.0062245 | G12: =Portefeuille!$N$12 -> 79.220004 | H12: =IF(D12<=3,'Courbe Scenarios'!$F$6,IF(D12<=7,'Courbe Scenarios'!$G$6,'Courbe Scenarios'!$H$6)) -> 0 | I12: =IF(C12="AAA",'Courbe Scenarios'!$I$6,IF(C12="AA",'Courbe Scenarios'!$J$6,IF(C12="A",'Courbe Scenarios'!$K$6,'Courbe Scenarios'!$L$6))) -> 0 | J12: =(H12+I12)/10000 -> 0 | K12: =E12*(-F12*J12+0.5*G12*J12^2) -> 0 | L12: =E12+K12 -> 705621.52
A13: Hausse parallele +100 pb | B13: B01 | C13: AAA | D13: 1 | E13: =Portefeuille!$K$5 -> 1958863.9 | F13: =Portefeuille!$M$5 -> 0.97943193 | G13: =Portefeuille!$N$5 -> 1.9185738 | H13: =IF(D13<=3,'Courbe Scenarios'!$F$7,IF(D13<=7,'Courbe Scenarios'!$G$7,'Courbe Scenarios'!$H$7)) -> 100 | I13: =IF(C13="AAA",'Courbe Scenarios'!$I$7,IF(C13="AA",'Courbe Scenarios'!$J$7,IF(C13="A",'Courbe Scenarios'!$K$7,'Courbe Scenarios'!$L$7))) -> 10 | J13: =(H13+I13)/10000 -> 0.011 | K13: =E13*(-F13*J13+0.5*G13*J13^2) -> -20876.939 | L13: =E13+K13 -> 1937986.9
A14: Hausse parallele +100 pb | B14: B02 | C14: AAA | D14: 3 | E14: =Portefeuille!$K$6 -> 1787085.5 | F14: =Portefeuille!$M$6 -> 2.8766061 | G14: =Portefeuille!$N$6 -> 11.178681 | H14: =IF(D14<=3,'Courbe Scenarios'!$F$7,IF(D14<=7,'Courbe Scenarios'!$G$7,'Courbe Scenarios'!$H$7)) -> 100 | I14: =IF(C14="AAA",'Courbe Scenarios'!$I$7,IF(C14="AA",'Courbe Scenarios'!$J$7,IF(C14="A",'Courbe Scenarios'!$K$7,'Courbe Scenarios'!$L$7))) -> 10 | J14: =(H14+I14)/10000 -> 0.011 | K14: =E14*(-F14*J14+0.5*G14*J14^2) -> -55339.527 | L14: =E14+K14 -> 1731745.9
A15: Hausse parallele +100 pb | B15: B03 | C15: AA | D15: 6 | E15: =Portefeuille!$K$7 -> 1520655.5 | F15: =Portefeuille!$M$7 -> 5.4787349 | G15: =Portefeuille!$N$7 -> 36.576187 | H15: =IF(D15<=3,'Courbe Scenarios'!$F$7,IF(D15<=7,'Courbe Scenarios'!$G$7,'Courbe Scenarios'!$H$7)) -> 100 | I15: =IF(C15="AAA",'Courbe Scenarios'!$I$7,IF(C15="AA",'Courbe Scenarios'!$J$7,IF(C15="A",'Courbe Scenarios'!$K$7,'Courbe Scenarios'!$L$7))) -> 15 | J15: =(H15+I15)/10000 -> 0.0115 | K15: =E15*(-F15*J15+0.5*G15*J15^2) -> -92131.726 | L15: =E15+K15 -> 1428523.7
A16: Hausse parallele +100 pb | B16: B04 | C16: A | D16: 2 | E16: =Portefeuille!$K$8 -> 1204592.3 | F16: =Portefeuille!$M$8 -> 1.9116995 | G16: =Portefeuille!$N$8 -> 5.5388839 | H16: =IF(D16<=3,'Courbe Scenarios'!$F$7,IF(D16<=7,'Courbe Scenarios'!$G$7,'Courbe Scenarios'!$H$7)) -> 100 | I16: =IF(C16="AAA",'Courbe Scenarios'!$I$7,IF(C16="AA",'Courbe Scenarios'!$J$7,IF(C16="A",'Courbe Scenarios'!$K$7,'Courbe Scenarios'!$L$7))) -> 25 | J16: =(H16+I16)/10000 -> 0.0125 | K16: =E16*(-F16*J16+0.5*G16*J16^2) -> -28263.974 | L16: =E16+K16 -> 1176328.4
A17: Hausse parallele +100 pb | B17: B05 | C17: A | D17: 4 | E17: =Portefeuille!$K$9 -> 1012886.4 | F17: =Portefeuille!$M$9 -> 3.6652201 | G17: =Portefeuille!$N$9 -> 17.39951 | H17: =IF(D17<=3,'Courbe Scenarios'!$F$7,IF(D17<=7,'Courbe Scenarios'!$G$7,'Courbe Scenarios'!$H$7)) -> 100 | I17: =IF(C17="AAA",'Courbe Scenarios'!$I$7,IF(C17="AA",'Courbe Scenarios'!$J$7,IF(C17="A",'Courbe Scenarios'!$K$7,'Courbe Scenarios'!$L$7))) -> 25 | J17: =(H17+I17)/10000 -> 0.0125 | K17: =E17*(-F17*J17+0.5*G17*J17^2) -> -45028.789 | L17: =E17+K17 -> 967857.57
A18: Hausse parallele +100 pb | B18: B06 | C18: BBB | D18: 5 | E18: =Portefeuille!$K$10 -> 908035.84 | F18: =Portefeuille!$M$10 -> 4.4497493 | G18: =Portefeuille!$N$10 -> 25.011612 | H18: =IF(D18<=3,'Courbe Scenarios'!$F$7,IF(D18<=7,'Courbe Scenarios'!$G$7,'Courbe Scenarios'!$H$7)) -> 100 | I18: =IF(C18="AAA",'Courbe Scenarios'!$I$7,IF(C18="AA",'Courbe Scenarios'!$J$7,IF(C18="A",'Courbe Scenarios'!$K$7,'Courbe Scenarios'!$L$7))) -> 35 | J18: =(H18+I18)/10000 -> 0.0135 | K18: =E18*(-F18*J18+0.5*G18*J18^2) -> -52477.6 | L18: =E18+K18 -> 855558.24
A19: Hausse parallele +100 pb | B19: B07 | C19: BBB | D19: 8 | E19: =Portefeuille!$K$11 -> 1130119.6 | F19: =Portefeuille!$M$11 -> 6.7739116 | G19: =Portefeuille!$N$11 -> 56.196614 | H19: =IF(D19<=3,'Courbe Scenarios'!$F$7,IF(D19<=7,'Courbe Scenarios'!$G$7,'Courbe Scenarios'!$H$7)) -> 100 | I19: =IF(C19="AAA",'Courbe Scenarios'!$I$7,IF(C19="AA",'Courbe Scenarios'!$J$7,IF(C19="A",'Courbe Scenarios'!$K$7,'Courbe Scenarios'!$L$7))) -> 35 | J19: =(H19+I19)/10000 -> 0.0135 | K19: =E19*(-F19*J19+0.5*G19*J19^2) -> -97559.708 | L19: =E19+K19 -> 1032559.9
A20: Hausse parallele +100 pb | B20: B08 | C20: BBB | D20: 10 | E20: =Portefeuille!$K$12 -> 705621.52 | F20: =Portefeuille!$M$12 -> 8.0062245 | G20: =Portefeuille!$N$12 -> 79.220004 | H20: =IF(D20<=3,'Courbe Scenarios'!$F$7,IF(D20<=7,'Courbe Scenarios'!$G$7,'Courbe Scenarios'!$H$7)) -> 100 | I20: =IF(C20="AAA",'Courbe Scenarios'!$I$7,IF(C20="AA",'Courbe Scenarios'!$J$7,IF(C20="A",'Courbe Scenarios'!$K$7,'Courbe Scenarios'!$L$7))) -> 35 | J20: =(H20+I20)/10000 -> 0.0135 | K20: =E20*(-F20*J20+0.5*G20*J20^2) -> -71172.591 | L20: =E20+K20 -> 634448.93
A21: Rally taux -75 pb | B21: B01 | C21: AAA | D21: 1 | E21: =Portefeuille!$K$5 -> 1958863.9 | F21: =Portefeuille!$M$5 -> 0.97943193 | G21: =Portefeuille!$N$5 -> 1.9185738 | H21: =IF(D21<=3,'Courbe Scenarios'!$F$8,IF(D21<=7,'Courbe Scenarios'!$G$8,'Courbe Scenarios'!$H$8)) -> -75 | I21: =IF(C21="AAA",'Courbe Scenarios'!$I$8,IF(C21="AA",'Courbe Scenarios'!$J$8,IF(C21="A",'Courbe Scenarios'!$K$8,'Courbe Scenarios'!$L$8))) -> -5 | J21: =(H21+I21)/10000 -> -0.008 | K21: =E21*(-F21*J21+0.5*G21*J21^2) -> 15468.854 | L21: =E21+K21 -> 1974332.7
A22: Rally taux -75 pb | B22: B02 | C22: AAA | D22: 3 | E22: =Portefeuille!$K$6 -> 1787085.5 | F22: =Portefeuille!$M$6 -> 2.8766061 | G22: =Portefeuille!$N$6 -> 11.178681 | H22: =IF(D22<=3,'Courbe Scenarios'!$F$8,IF(D22<=7,'Courbe Scenarios'!$G$8,'Courbe Scenarios'!$H$8)) -> -75 | I22: =IF(C22="AAA",'Courbe Scenarios'!$I$8,IF(C22="AA",'Courbe Scenarios'!$J$8,IF(C22="A",'Courbe Scenarios'!$K$8,'Courbe Scenarios'!$L$8))) -> -5 | J22: =(H22+I22)/10000 -> -0.008 | K22: =E22*(-F22*J22+0.5*G22*J22^2) -> 41765.2 | L22: =E22+K22 -> 1828850.7
A23: Rally taux -75 pb | B23: B03 | C23: AA | D23: 6 | E23: =Portefeuille!$K$7 -> 1520655.5 | F23: =Portefeuille!$M$7 -> 5.4787349 | G23: =Portefeuille!$N$7 -> 36.576187 | H23: =IF(D23<=3,'Courbe Scenarios'!$F$8,IF(D23<=7,'Courbe Scenarios'!$G$8,'Courbe Scenarios'!$H$8)) -> -75 | I23: =IF(C23="AAA",'Courbe Scenarios'!$I$8,IF(C23="AA",'Courbe Scenarios'!$J$8,IF(C23="A",'Courbe Scenarios'!$K$8,'Courbe Scenarios'!$L$8))) -> -8 | J23: =(H23+I23)/10000 -> -0.0083 | K23: =E23*(-F23*J23+0.5*G23*J23^2) -> 71065.349 | L23: =E23+K23 -> 1591720.8
A24: Rally taux -75 pb | B24: B04 | C24: A | D24: 2 | E24: =Portefeuille!$K$8 -> 1204592.3 | F24: =Portefeuille!$M$8 -> 1.9116995 | G24: =Portefeuille!$N$8 -> 5.5388839 | H24: =IF(D24<=3,'Courbe Scenarios'!$F$8,IF(D24<=7,'Courbe Scenarios'!$G$8,'Courbe Scenarios'!$H$8)) -> -75 | I24: =IF(C24="AAA",'Courbe Scenarios'!$I$8,IF(C24="AA",'Courbe Scenarios'!$J$8,IF(C24="A",'Courbe Scenarios'!$K$8,'Courbe Scenarios'!$L$8))) -> -10 | J24: =(H24+I24)/10000 -> -0.0085 | K24: =E24*(-F24*J24+0.5*G24*J24^2) -> 19814.987 | L24: =E24+K24 -> 1224407.3
A25: Rally taux -75 pb | B25: B05 | C25: A | D25: 4 | E25: =Portefeuille!$K$9 -> 1012886.4 | F25: =Portefeuille!$M$9 -> 3.6652201 | G25: =Portefeuille!$N$9 -> 17.39951 | H25: =IF(D25<=3,'Courbe Scenarios'!$F$8,IF(D25<=7,'Courbe Scenarios'!$G$8,'Courbe Scenarios'!$H$8)) -> -75 | I25: =IF(C25="AAA",'Courbe Scenarios'!$I$8,IF(C25="AA",'Courbe Scenarios'!$J$8,IF(C25="A",'Courbe Scenarios'!$K$8,'Courbe Scenarios'!$L$8))) -> -10 | J25: =(H25+I25)/10000 -> -0.0085 | K25: =E25*(-F25*J25+0.5*G25*J25^2) -> 32192.494 | L25: =E25+K25 -> 1045078.8
A26: Rally taux -75 pb | B26: B06 | C26: BBB | D26: 5 | E26: =Portefeuille!$K$10 -> 908035.84 | F26: =Portefeuille!$M$10 -> 4.4497493 | G26: =Portefeuille!$N$10 -> 25.011612 | H26: =IF(D26<=3,'Courbe Scenarios'!$F$8,IF(D26<=7,'Courbe Scenarios'!$G$8,'Courbe Scenarios'!$H$8)) -> -75 | I26: =IF(C26="AAA",'Courbe Scenarios'!$I$8,IF(C26="AA",'Courbe Scenarios'!$J$8,IF(C26="A",'Courbe Scenarios'!$K$8,'Courbe Scenarios'!$L$8))) -> -10 | J26: =(H26+I26)/10000 -> -0.0085 | K26: =E26*(-F26*J26+0.5*G26*J26^2) -> 35164.972 | L26: =E26+K26 -> 943200.81
A27: Rally taux -75 pb | B27: B07 | C27: BBB | D27: 8 | E27: =Portefeuille!$K$11 -> 1130119.6 | F27: =Portefeuille!$M$11 -> 6.7739116 | G27: =Portefeuille!$N$11 -> 56.196614 | H27: =IF(D27<=3,'Courbe Scenarios'!$F$8,IF(D27<=7,'Courbe Scenarios'!$G$8,'Courbe Scenarios'!$H$8)) -> -75 | I27: =IF(C27="AAA",'Courbe Scenarios'!$I$8,IF(C27="AA",'Courbe Scenarios'!$J$8,IF(C27="A",'Courbe Scenarios'!$K$8,'Courbe Scenarios'!$L$8))) -> -10 | J27: =(H27+I27)/10000 -> -0.0085 | K27: =E27*(-F27*J27+0.5*G27*J27^2) -> 67364.564 | L27: =E27+K27 -> 1197484.1
A28: Rally taux -75 pb | B28: B08 | C28: BBB | D28: 10 | E28: =Portefeuille!$K$12 -> 705621.52 | F28: =Portefeuille!$M$12 -> 8.0062245 | G28: =Portefeuille!$N$12 -> 79.220004 | H28: =IF(D28<=3,'Courbe Scenarios'!$F$8,IF(D28<=7,'Courbe Scenarios'!$G$8,'Courbe Scenarios'!$H$8)) -> -75 | I28: =IF(C28="AAA",'Courbe Scenarios'!$I$8,IF(C28="AA",'Courbe Scenarios'!$J$8,IF(C28="A",'Courbe Scenarios'!$K$8,'Courbe Scenarios'!$L$8))) -> -10 | J28: =(H28+I28)/10000 -> -0.0085 | K28: =E28*(-F28*J28+0.5*G28*J28^2) -> 50038.96 | L28: =E28+K28 -> 755660.48
A29: Ecartement credit | B29: B01 | C29: AAA | D29: 1 | E29: =Portefeuille!$K$5 -> 1958863.9 | F29: =Portefeuille!$M$5 -> 0.97943193 | G29: =Portefeuille!$N$5 -> 1.9185738 | H29: =IF(D29<=3,'Courbe Scenarios'!$F$9,IF(D29<=7,'Courbe Scenarios'!$G$9,'Courbe Scenarios'!$H$9)) -> 0 | I29: =IF(C29="AAA",'Courbe Scenarios'!$I$9,IF(C29="AA",'Courbe Scenarios'!$J$9,IF(C29="A",'Courbe Scenarios'!$K$9,'Courbe Scenarios'!$L$9))) -> 20 | J29: =(H29+I29)/10000 -> 0.002 | K29: =E29*(-F29*J29+0.5*G29*J29^2) -> -3829.6312 | L29: =E29+K29 -> 1955034.2
A30: Ecartement credit | B30: B02 | C30: AAA | D30: 3 | E30: =Portefeuille!$K$6 -> 1787085.5 | F30: =Portefeuille!$M$6 -> 2.8766061 | G30: =Portefeuille!$N$6 -> 11.178681 | H30: =IF(D30<=3,'Courbe Scenarios'!$F$9,IF(D30<=7,'Courbe Scenarios'!$G$9,'Courbe Scenarios'!$H$9)) -> 0 | I30: =IF(C30="AAA",'Courbe Scenarios'!$I$9,IF(C30="AA",'Courbe Scenarios'!$J$9,IF(C30="A",'Courbe Scenarios'!$K$9,'Courbe Scenarios'!$L$9))) -> 20 | J30: =(H30+I30)/10000 -> 0.002 | K30: =E30*(-F30*J30+0.5*G30*J30^2) -> -10241.527 | L30: =E30+K30 -> 1776843.9
A31: Ecartement credit | B31: B03 | C31: AA | D31: 6 | E31: =Portefeuille!$K$7 -> 1520655.5 | F31: =Portefeuille!$M$7 -> 5.4787349 | G31: =Portefeuille!$N$7 -> 36.576187 | H31: =IF(D31<=3,'Courbe Scenarios'!$F$9,IF(D31<=7,'Courbe Scenarios'!$G$9,'Courbe Scenarios'!$H$9)) -> 0 | I31: =IF(C31="AAA",'Courbe Scenarios'!$I$9,IF(C31="AA",'Courbe Scenarios'!$J$9,IF(C31="A",'Courbe Scenarios'!$K$9,'Courbe Scenarios'!$L$9))) -> 35 | J31: =(H31+I31)/10000 -> 0.0035 | K31: =E31*(-F31*J31+0.5*G31*J31^2) -> -28818.767 | L31: =E31+K31 -> 1491836.7
A32: Ecartement credit | B32: B04 | C32: A | D32: 2 | E32: =Portefeuille!$K$8 -> 1204592.3 | F32: =Portefeuille!$M$8 -> 1.9116995 | G32: =Portefeuille!$N$8 -> 5.5388839 | H32: =IF(D32<=3,'Courbe Scenarios'!$F$9,IF(D32<=7,'Courbe Scenarios'!$G$9,'Courbe Scenarios'!$H$9)) -> 0 | I32: =IF(C32="AAA",'Courbe Scenarios'!$I$9,IF(C32="AA",'Courbe Scenarios'!$J$9,IF(C32="A",'Courbe Scenarios'!$K$9,'Courbe Scenarios'!$L$9))) -> 75 | J32: =(H32+I32)/10000 -> 0.0075 | K32: =E32*(-F32*J32+0.5*G32*J32^2) -> -17083.486 | L32: =E32+K32 -> 1187508.8
A33: Ecartement credit | B33: B05 | C33: A | D33: 4 | E33: =Portefeuille!$K$9 -> 1012886.4 | F33: =Portefeuille!$M$9 -> 3.6652201 | G33: =Portefeuille!$N$9 -> 17.39951 | H33: =IF(D33<=3,'Courbe Scenarios'!$F$9,IF(D33<=7,'Courbe Scenarios'!$G$9,'Courbe Scenarios'!$H$9)) -> 0 | I33: =IF(C33="AAA",'Courbe Scenarios'!$I$9,IF(C33="AA",'Courbe Scenarios'!$J$9,IF(C33="A",'Courbe Scenarios'!$K$9,'Courbe Scenarios'!$L$9))) -> 75 | J33: =(H33+I33)/10000 -> 0.0075 | K33: =E33*(-F33*J33+0.5*G33*J33^2) -> -27347.718 | L33: =E33+K33 -> 985538.64
A34: Ecartement credit | B34: B06 | C34: BBB | D34: 5 | E34: =Portefeuille!$K$10 -> 908035.84 | F34: =Portefeuille!$M$10 -> 4.4497493 | G34: =Portefeuille!$N$10 -> 25.011612 | H34: =IF(D34<=3,'Courbe Scenarios'!$F$9,IF(D34<=7,'Courbe Scenarios'!$G$9,'Courbe Scenarios'!$H$9)) -> 0 | I34: =IF(C34="AAA",'Courbe Scenarios'!$I$9,IF(C34="AA",'Courbe Scenarios'!$J$9,IF(C34="A",'Courbe Scenarios'!$K$9,'Courbe Scenarios'!$L$9))) -> 150 | J34: =(H34+I34)/10000 -> 0.015 | K34: =E34*(-F34*J34+0.5*G34*J34^2) -> -58052.941 | L34: =E34+K34 -> 849982.9
A35: Ecartement credit | B35: B07 | C35: BBB | D35: 8 | E35: =Portefeuille!$K$11 -> 1130119.6 | F35: =Portefeuille!$M$11 -> 6.7739116 | G35: =Portefeuille!$N$11 -> 56.196614 | H35: =IF(D35<=3,'Courbe Scenarios'!$F$9,IF(D35<=7,'Courbe Scenarios'!$G$9,'Courbe Scenarios'!$H$9)) -> 0 | I35: =IF(C35="AAA",'Courbe Scenarios'!$I$9,IF(C35="AA",'Courbe Scenarios'!$J$9,IF(C35="A",'Courbe Scenarios'!$K$9,'Courbe Scenarios'!$L$9))) -> 150 | J35: =(H35+I35)/10000 -> 0.015 | K35: =E35*(-F35*J35+0.5*G35*J35^2) -> -107685.2 | L35: =E35+K35 -> 1022434.4
A36: Ecartement credit | B36: B08 | C36: BBB | D36: 10 | E36: =Portefeuille!$K$12 -> 705621.52 | F36: =Portefeuille!$M$12 -> 8.0062245 | G36: =Portefeuille!$N$12 -> 79.220004 | H36: =IF(D36<=3,'Courbe Scenarios'!$F$9,IF(D36<=7,'Courbe Scenarios'!$G$9,'Courbe Scenarios'!$H$9)) -> 0 | I36: =IF(C36="AAA",'Courbe Scenarios'!$I$9,IF(C36="AA",'Courbe Scenarios'!$J$9,IF(C36="A",'Courbe Scenarios'!$K$9,'Courbe Scenarios'!$L$9))) -> 150 | J36: =(H36+I36)/10000 -> 0.015 | K36: =E36*(-F36*J36+0.5*G36*J36^2) -> -78451.789 | L36: =E36+K36 -> 627169.73
A37: Bear steepener | B37: B01 | C37: AAA | D37: 1 | E37: =Portefeuille!$K$5 -> 1958863.9 | F37: =Portefeuille!$M$5 -> 0.97943193 | G37: =Portefeuille!$N$5 -> 1.9185738 | H37: =IF(D37<=3,'Courbe Scenarios'!$F$10,IF(D37<=7,'Courbe Scenarios'!$G$10,'Courbe Scenarios'!$H$10)) -> 25 | I37: =IF(C37="AAA",'Courbe Scenarios'!$I$10,IF(C37="AA",'Courbe Scenarios'!$J$10,IF(C37="A",'Courbe Scenarios'!$K$10,'Courbe Scenarios'!$L$10))) -> 10 | J37: =(H37+I37)/10000 -> 0.0035 | K37: =E37*(-F37*J37+0.5*G37*J37^2) -> -6691.9892 | L37: =E37+K37 -> 1952171.9
A38: Bear steepener | B38: B02 | C38: AAA | D38: 3 | E38: =Portefeuille!$K$6 -> 1787085.5 | F38: =Portefeuille!$M$6 -> 2.8766061 | G38: =Portefeuille!$N$6 -> 11.178681 | H38: =IF(D38<=3,'Courbe Scenarios'!$F$10,IF(D38<=7,'Courbe Scenarios'!$G$10,'Courbe Scenarios'!$H$10)) -> 25 | I38: =IF(C38="AAA",'Courbe Scenarios'!$I$10,IF(C38="AA",'Courbe Scenarios'!$J$10,IF(C38="A",'Courbe Scenarios'!$K$10,'Courbe Scenarios'!$L$10))) -> 10 | J38: =(H38+I38)/10000 -> 0.0035 | K38: =E38*(-F38*J38+0.5*G38*J38^2) -> -17870.233 | L38: =E38+K38 -> 1769215.2
A39: Bear steepener | B39: B03 | C39: AA | D39: 6 | E39: =Portefeuille!$K$7 -> 1520655.5 | F39: =Portefeuille!$M$7 -> 5.4787349 | G39: =Portefeuille!$N$7 -> 36.576187 | H39: =IF(D39<=3,'Courbe Scenarios'!$F$10,IF(D39<=7,'Courbe Scenarios'!$G$10,'Courbe Scenarios'!$H$10)) -> 75 | I39: =IF(C39="AAA",'Courbe Scenarios'!$I$10,IF(C39="AA",'Courbe Scenarios'!$J$10,IF(C39="A",'Courbe Scenarios'!$K$10,'Courbe Scenarios'!$L$10))) -> 15 | J39: =(H39+I39)/10000 -> 0.009 | K39: =E39*(-F39*J39+0.5*G39*J39^2) -> -72728.812 | L39: =E39+K39 -> 1447926.7
A40: Bear steepener | B40: B04 | C40: A | D40: 2 | E40: =Portefeuille!$K$8 -> 1204592.3 | F40: =Portefeuille!$M$8 -> 1.9116995 | G40: =Portefeuille!$N$8 -> 5.5388839 | H40: =IF(D40<=3,'Courbe Scenarios'!$F$10,IF(D40<=7,'Courbe Scenarios'!$G$10,'Courbe Scenarios'!$H$10)) -> 25 | I40: =IF(C40="AAA",'Courbe Scenarios'!$I$10,IF(C40="AA",'Courbe Scenarios'!$J$10,IF(C40="A",'Courbe Scenarios'!$K$10,'Courbe Scenarios'!$L$10))) -> 25 | J40: =(H40+I40)/10000 -> 0.005 | K40: =E40*(-F40*J40+0.5*G40*J40^2) -> -11430.692 | L40: =E40+K40 -> 1193161.6
A41: Bear steepener | B41: B05 | C41: A | D41: 4 | E41: =Portefeuille!$K$9 -> 1012886.4 | F41: =Portefeuille!$M$9 -> 3.6652201 | G41: =Portefeuille!$N$9 -> 17.39951 | H41: =IF(D41<=3,'Courbe Scenarios'!$F$10,IF(D41<=7,'Courbe Scenarios'!$G$10,'Courbe Scenarios'!$H$10)) -> 75 | I41: =IF(C41="AAA",'Courbe Scenarios'!$I$10,IF(C41="AA",'Courbe Scenarios'!$J$10,IF(C41="A",'Courbe Scenarios'!$K$10,'Courbe Scenarios'!$L$10))) -> 25 | J41: =(H41+I41)/10000 -> 0.01 | K41: =E41*(-F41*J41+0.5*G41*J41^2) -> -36243.328 | L41: =E41+K41 -> 976643.03
A42: Bear steepener | B42: B06 | C42: BBB | D42: 5 | E42: =Portefeuille!$K$10 -> 908035.84 | F42: =Portefeuille!$M$10 -> 4.4497493 | G42: =Portefeuille!$N$10 -> 25.011612 | H42: =IF(D42<=3,'Courbe Scenarios'!$F$10,IF(D42<=7,'Courbe Scenarios'!$G$10,'Courbe Scenarios'!$H$10)) -> 75 | I42: =IF(C42="AAA",'Courbe Scenarios'!$I$10,IF(C42="AA",'Courbe Scenarios'!$J$10,IF(C42="A",'Courbe Scenarios'!$K$10,'Courbe Scenarios'!$L$10))) -> 50 | J42: =(H42+I42)/10000 -> 0.0125 | K42: =E42*(-F42*J42+0.5*G42*J42^2) -> -48732.317 | L42: =E42+K42 -> 859303.52
A43: Bear steepener | B43: B07 | C43: BBB | D43: 8 | E43: =Portefeuille!$K$11 -> 1130119.6 | F43: =Portefeuille!$M$11 -> 6.7739116 | G43: =Portefeuille!$N$11 -> 56.196614 | H43: =IF(D43<=3,'Courbe Scenarios'!$F$10,IF(D43<=7,'Courbe Scenarios'!$G$10,'Courbe Scenarios'!$H$10)) -> 125 | I43: =IF(C43="AAA",'Courbe Scenarios'!$I$10,IF(C43="AA",'Courbe Scenarios'!$J$10,IF(C43="A",'Courbe Scenarios'!$K$10,'Courbe Scenarios'!$L$10))) -> 50 | J43: =(H43+I43)/10000 -> 0.0175 | K43: =E43*(-F43*J43+0.5*G43*J43^2) -> -124243.48 | L43: =E43+K43 -> 1005876.1
A44: Bear steepener | B44: B08 | C44: BBB | D44: 10 | E44: =Portefeuille!$K$12 -> 705621.52 | F44: =Portefeuille!$M$12 -> 8.0062245 | G44: =Portefeuille!$N$12 -> 79.220004 | H44: =IF(D44<=3,'Courbe Scenarios'!$F$10,IF(D44<=7,'Courbe Scenarios'!$G$10,'Courbe Scenarios'!$H$10)) -> 125 | I44: =IF(C44="AAA",'Courbe Scenarios'!$I$10,IF(C44="AA",'Courbe Scenarios'!$J$10,IF(C44="A",'Courbe Scenarios'!$K$10,'Courbe Scenarios'!$L$10))) -> 50 | J44: =(H44+I44)/10000 -> 0.0175 | K44: =E44*(-F44*J44+0.5*G44*J44^2) -> -90304.289 | L44: =E44+K44 -> 615317.23
A47: Synthese des scenarios | B47: Synthese des scenarios | C47: Synthese des scenarios | D47: Synthese des scenarios
A48: Scenario | B48: PnL EUR | C48: Impact % | D48: Valeur stressee
A49: Base | B49: =SUM(K5:K12) -> 0 | C49: =B49/Portefeuille!$K$13 -> 0 | D49: =SUM(L5:L12) -> 10227860
A50: Hausse parallele +100 pb | B50: =SUM(K13:K20) -> -462850.85 | C50: =B50/Portefeuille!$K$13 -> -0.045253928 | D50: =SUM(L13:L20) -> 9765009.6
A51: Rally taux -75 pb | B51: =SUM(K21:K28) -> 332875.38 | C51: =B51/Portefeuille!$K$13 -> 0.032545945 | D51: =SUM(L21:L28) -> 10560736
A52: Ecartement credit | B52: =SUM(K29:K36) -> -331511.06 | C52: =B52/Portefeuille!$K$13 -> -0.032412552 | D52: =SUM(L29:L36) -> 9896349.3
A53: Bear steepener | B53: =SUM(K37:K44) -> -408245.14 | C53: =B53/Portefeuille!$K$13 -> -0.039915009 | D53: =SUM(L37:L44) -> 9819615.3

Sheet Couverture
A1: Couverture indicative du risque de taux | B1: Couverture indicative du risque de taux | C1: Couverture indicative du risque de taux | D1: Couverture indicative du risque de taux | E1: Couverture indicative du risque de taux | F1: Couverture indicative du risque de taux | G1: Couverture indicative du risque de taux | H1: Couverture indicative du risque de taux | I1: Couverture indicative du risque de taux | J1: Couverture indicative du risque de taux
A2: Neutralisation de la DV01 par un future taux EUR illustratif | B2: Neutralisation de la DV01 par un future taux EUR illustratif | C2: Neutralisation de la DV01 par un future taux EUR illustratif | D2: Neutralisation de la DV01 par un future taux EUR illustratif | E2: Neutralisation de la DV01 par un future taux EUR illustratif | F2: Neutralisation de la DV01 par un future taux EUR illustratif | G2: Neutralisation de la DV01 par un future taux EUR illustratif | H2: Neutralisation de la DV01 par un future taux EUR illustratif | I2: Neutralisation de la DV01 par un future taux EUR illustratif | J2: Neutralisation de la DV01 par un future taux EUR illustratif
A4: Parametres et resultat | B4: Parametres et resultat | C4: Parametres et resultat | D4: Parametres et resultat
A5: Indicateur | B5: Valeur
A6: DV01 portefeuille EUR/pb | B6: =Portefeuille!$O$13 -> 3875.1079
A7: DV01 par contrat EUR/pb | B7: 85
A8: Nombre de contrats | B8: =ROUND(-B6/B7,0) -> -46
A9: DV01 residuelle EUR/pb | B9: =B6+B8*B7 -> -34.892083
A10: Efficacite de couverture | B10: =1-ABS(B9/B6) -> 0.99099584
A11: Sens de la position | B11: =IF(B8<0,"Vendre futures","Acheter futures") -> Vendre futures
A14: Mesure | B14: Avant | C14: Apres
A15: DV01 absolue | B15: =ABS(B6) -> 3875.1079 | C15: =ABS(B9) -> 34.892083
A16: Reduction | B16: 0 | C16: =B15-C15 -> 3840.2158
A19: Limite : la DV01 contractuelle d'un future depend du contrat, de son facteur de conversion et du CTD. La valeur de 85 EUR/pb est une hypothese editable destinee a illustrer la logique de couverture. | B19: Limite : la DV01 contractuelle d'un future depend du contrat, de son facteur de conversion et du CTD. La valeur de 85 EUR/pb est une hypothese editable destinee a illustrer la logique de couverture. | C19: Limite : la DV01 contractuelle d'un future depend du contrat, de son facteur de conversion et du CTD. La valeur de 85 EUR/pb est une hypothese editable destinee a illustrer la logique de couverture. | D19: Limite : la DV01 contractuelle d'un future depend du contrat, de son facteur de conversion et du CTD. La valeur de 85 EUR/pb est une hypothese editable destinee a illustrer la logique de couverture. | E19: Limite : la DV01 contractuelle d'un future depend du contrat, de son facteur de conversion et du CTD. La valeur de 85 EUR/pb est une hypothese editable destinee a illustrer la logique de couverture. | F19: Limite : la DV01 contractuelle d'un future depend du contrat, de son facteur de conversion et du CTD. La valeur de 85 EUR/pb est une hypothese editable destinee a illustrer la logique de couverture. | G19: Limite : la DV01 contractuelle d'un future depend du contrat, de son facteur de conversion et du CTD. La valeur de 85 EUR/pb est une hypothese editable destinee a illustrer la logique de couverture. | H19: Limite : la DV01 contractuelle d'un future depend du contrat, de son facteur de conversion et du CTD. La valeur de 85 EUR/pb est une hypothese editable destinee a illustrer la logique de couverture. | I19: Limite : la DV01 contractuelle d'un future depend du contrat, de son facteur de conversion et du CTD. La valeur de 85 EUR/pb est une hypothese editable destinee a illustrer la logique de couverture. | J19: Limite : la DV01 contractuelle d'un future depend du contrat, de son facteur de conversion et du CTD. La valeur de 85 EUR/pb est une hypothese editable destinee a illustrer la logique de couverture.
A20: Limite : la DV01 contractuelle d'un future depend du contrat, de son facteur de conversion et du CTD. La valeur de 85 EUR/pb est une hypothese editable destinee a illustrer la logique de couverture. | B20: Limite : la DV01 contractuelle d'un future depend du contrat, de son facteur de conversion et du CTD. La valeur de 85 EUR/pb est une hypothese editable destinee a illustrer la logique de couverture. | C20: Limite : la DV01 contractuelle d'un future depend du contrat, de son facteur de conversion et du CTD. La valeur de 85 EUR/pb est une hypothese editable destinee a illustrer la logique de couverture. | D20: Limite : la DV01 contractuelle d'un future depend du contrat, de son facteur de conversion et du CTD. La valeur de 85 EUR/pb est une hypothese editable destinee a illustrer la logique de couverture. | E20: Limite : la DV01 contractuelle d'un future depend du contrat, de son facteur de conversion et du CTD. La valeur de 85 EUR/pb est une hypothese editable destinee a illustrer la logique de couverture. | F20: Limite : la DV01 contractuelle d'un future depend du contrat, de son facteur de conversion et du CTD. La valeur de 85 EUR/pb est une hypothese editable destinee a illustrer la logique de couverture. | G20: Limite : la DV01 contractuelle d'un future depend du contrat, de son facteur de conversion et du CTD. La valeur de 85 EUR/pb est une hypothese editable destinee a illustrer la logique de couverture. | H20: Limite : la DV01 contractuelle d'un future depend du contrat, de son facteur de conversion et du CTD. La valeur de 85 EUR/pb est une hypothese editable destinee a illustrer la logique de couverture. | I20: Limite : la DV01 contractuelle d'un future depend du contrat, de son facteur de conversion et du CTD. La valeur de 85 EUR/pb est une hypothese editable destinee a illustrer la logique de couverture. | J20: Limite : la DV01 contractuelle d'un future depend du contrat, de son facteur de conversion et du CTD. La valeur de 85 EUR/pb est une hypothese editable destinee a illustrer la logique de couverture.
A21: Limite : la DV01 contractuelle d'un future depend du contrat, de son facteur de conversion et du CTD. La valeur de 85 EUR/pb est une hypothese editable destinee a illustrer la logique de couverture. | B21: Limite : la DV01 contractuelle d'un future depend du contrat, de son facteur de conversion et du CTD. La valeur de 85 EUR/pb est une hypothese editable destinee a illustrer la logique de couverture. | C21: Limite : la DV01 contractuelle d'un future depend du contrat, de son facteur de conversion et du CTD. La valeur de 85 EUR/pb est une hypothese editable destinee a illustrer la logique de couverture. | D21: Limite : la DV01 contractuelle d'un future depend du contrat, de son facteur de conversion et du CTD. La valeur de 85 EUR/pb est une hypothese editable destinee a illustrer la logique de couverture. | E21: Limite : la DV01 contractuelle d'un future depend du contrat, de son facteur de conversion et du CTD. La valeur de 85 EUR/pb est une hypothese editable destinee a illustrer la logique de couverture. | F21: Limite : la DV01 contractuelle d'un future depend du contrat, de son facteur de conversion et du CTD. La valeur de 85 EUR/pb est une hypothese editable destinee a illustrer la logique de couverture. | G21: Limite : la DV01 contractuelle d'un future depend du contrat, de son facteur de conversion et du CTD. La valeur de 85 EUR/pb est une hypothese editable destinee a illustrer la logique de couverture. | H21: Limite : la DV01 contractuelle d'un future depend du contrat, de son facteur de conversion et du CTD. La valeur de 85 EUR/pb est une hypothese editable destinee a illustrer la logique de couverture. | I21: Limite : la DV01 contractuelle d'un future depend du contrat, de son facteur de conversion et du CTD. La valeur de 85 EUR/pb est une hypothese editable destinee a illustrer la logique de couverture. | J21: Limite : la DV01 contractuelle d'un future depend du contrat, de son facteur de conversion et du CTD. La valeur de 85 EUR/pb est une hypothese editable destinee a illustrer la logique de couverture.

Sheet Collateral
A1: Suivi du collateral et appels de marge | B1: Suivi du collateral et appels de marge | C1: Suivi du collateral et appels de marge | D1: Suivi du collateral et appels de marge | E1: Suivi du collateral et appels de marge | F1: Suivi du collateral et appels de marge | G1: Suivi du collateral et appels de marge | H1: Suivi du collateral et appels de marge | I1: Suivi du collateral et appels de marge | J1: Suivi du collateral et appels de marge | K1: Suivi du collateral et appels de marge | L1: Suivi du collateral et appels de marge | M1: Suivi du collateral et appels de marge | N1: Suivi du collateral et appels de marge | O1: Suivi du collateral et appels de marge | P1: Suivi du collateral et appels de marge
A2: MtM positif = creance / collateral positif = recu | Seuils de reconciliation editables | B2: MtM positif = creance / collateral positif = recu | Seuils de reconciliation editables | C2: MtM positif = creance / collateral positif = recu | Seuils de reconciliation editables | D2: MtM positif = creance / collateral positif = recu | Seuils de reconciliation editables | E2: MtM positif = creance / collateral positif = recu | Seuils de reconciliation editables | F2: MtM positif = creance / collateral positif = recu | Seuils de reconciliation editables | G2: MtM positif = creance / collateral positif = recu | Seuils de reconciliation editables | H2: MtM positif = creance / collateral positif = recu | Seuils de reconciliation editables | I2: MtM positif = creance / collateral positif = recu | Seuils de reconciliation editables | J2: MtM positif = creance / collateral positif = recu | Seuils de reconciliation editables | K2: MtM positif = creance / collateral positif = recu | Seuils de reconciliation editables | L2: MtM positif = creance / collateral positif = recu | Seuils de reconciliation editables | M2: MtM positif = creance / collateral positif = recu | Seuils de reconciliation editables | N2: MtM positif = creance / collateral positif = recu | Seuils de reconciliation editables | O2: MtM positif = creance / collateral positif = recu | Seuils de reconciliation editables | P2: MtM positif = creance / collateral positif = recu | Seuils de reconciliation editables
A4: Trade ID | B4: Instrument | C4: Notionnel interne | D4: Notionnel CP | E4: MtM interne | F4: MtM CP | G4: Collateral interne | H4: Collateral CP | I4: Seuil | J4: MTA | K4: Collateral requis | L4: Appel de marge | M4: Ecart notionnel | N4: Ecart MtM | O4: Ecart collateral | P4: Statut
A5: D01 | B5: IRS EUR 5Y | C5: 5000000 | D5: 5000000 | E5: 180000 | F5: 177000 | G5: 150000 | H5: 150000 | I5: 25000 | J5: 10000 | K5: =IF(E5>=0,1,-1)*MAX(ABS(E5)-I5,0) -> 155000 | L5: =IF(ABS(K5-G5)>=J5,K5-G5,0) -> 0 | M5: =C5-D5 -> 0 | N5: =E5-F5 -> 3000 | O5: =G5-H5 -> 0 | P5: =IF(OR(ABS(M5)>1000,ABS(N5)>5000,ABS(O5)>5000),"EXCEPTION","OK") -> OK
A6: D02 | B6: IRS EUR 10Y | C6: 8000000 | D6: 7980000 | E6: -260000 | F6: -272000 | G6: -220000 | H6: -220000 | I6: 25000 | J6: 10000 | K6: =IF(E6>=0,1,-1)*MAX(ABS(E6)-I6,0) -> -235000 | L6: =IF(ABS(K6-G6)>=J6,K6-G6,0) -> -15000 | M6: =C6-D6 -> 20000 | N6: =E6-F6 -> 12000 | O6: =G6-H6 -> 0 | P6: =IF(OR(ABS(M6)>1000,ABS(N6)>5000,ABS(O6)>5000),"EXCEPTION","OK") -> EXCEPTION
A7: D03 | B7: CDS iTraxx 5Y | C7: 3000000 | D7: 3000000 | E7: 95000 | F7: 92500 | G7: 50000 | H7: 45000 | I7: 20000 | J7: 5000 | K7: =IF(E7>=0,1,-1)*MAX(ABS(E7)-I7,0) -> 75000 | L7: =IF(ABS(K7-G7)>=J7,K7-G7,0) -> 25000 | M7: =C7-D7 -> 0 | N7: =E7-F7 -> 2500 | O7: =G7-H7 -> 5000 | P7: =IF(OR(ABS(M7)>1000,ABS(N7)>5000,ABS(O7)>5000),"EXCEPTION","OK") -> OK
A8: D04 | B8: Swaption EUR | C8: 2500000 | D8: 2500000 | E8: 60000 | F8: 58000 | G8: 0 | H8: 0 | I8: 50000 | J8: 10000 | K8: =IF(E8>=0,1,-1)*MAX(ABS(E8)-I8,0) -> 10000 | L8: =IF(ABS(K8-G8)>=J8,K8-G8,0) -> 10000 | M8: =C8-D8 -> 0 | N8: =E8-F8 -> 2000 | O8: =G8-H8 -> 0 | P8: =IF(OR(ABS(M8)>1000,ABS(N8)>5000,ABS(O8)>5000),"EXCEPTION","OK") -> OK
A9: D05 | B9: Equity Swap | C9: 1500000 | D9: 1500000 | E9: -140000 | F9: -137000 | G9: -110000 | H9: -105000 | I9: 25000 | J9: 10000 | K9: =IF(E9>=0,1,-1)*MAX(ABS(E9)-I9,0) -> -115000 | L9: =IF(ABS(K9-G9)>=J9,K9-G9,0) -> 0 | M9: =C9-D9 -> 0 | N9: =E9-F9 -> -3000 | O9: =G9-H9 -> -5000 | P9: =IF(OR(ABS(M9)>1000,ABS(N9)>5000,ABS(O9)>5000),"EXCEPTION","OK") -> OK
A10: D06 | B10: IRS EUR 2Y | C10: 2000000 | D10: 2000000 | E10: 35000 | F10: 34000 | G10: 0 | H10: 0 | I10: 25000 | J10: 5000 | K10: =IF(E10>=0,1,-1)*MAX(ABS(E10)-I10,0) -> 10000 | L10: =IF(ABS(K10-G10)>=J10,K10-G10,0) -> 10000 | M10: =C10-D10 -> 0 | N10: =E10-F10 -> 1000 | O10: =G10-H10 -> 0 | P10: =IF(OR(ABS(M10)>1000,ABS(N10)>5000,ABS(O10)>5000),"EXCEPTION","OK") -> OK
A13: Synthese operationnelle | B13: Synthese operationnelle | C13: Synthese operationnelle | D13: Synthese operationnelle | E13: Synthese operationnelle | F13: Synthese operationnelle
A14: Indicateur | B14: Valeur
A15: Appels a recevoir | B15: =SUMIF(L5:L10,">0",L5:L10) -> 45000
A16: Appels a poster | B16: =SUMIF(L5:L10,"<0",L5:L10) -> -15000
A17: Exceptions | B17: =COUNTIF(P5:P10,"EXCEPTION") -> 1

Sheet Reconciliation
A1: Rapprochement des operations obligataires | B1: Rapprochement des operations obligataires | C1: Rapprochement des operations obligataires | D1: Rapprochement des operations obligataires | E1: Rapprochement des operations obligataires | F1: Rapprochement des operations obligataires | G1: Rapprochement des operations obligataires | H1: Rapprochement des operations obligataires | I1: Rapprochement des operations obligataires | J1: Rapprochement des operations obligataires | K1: Rapprochement des operations obligataires | L1: Rapprochement des operations obligataires
A2: Comparaison systeme interne / depositaire avec seuils d'exception | B2: Comparaison systeme interne / depositaire avec seuils d'exception | C2: Comparaison systeme interne / depositaire avec seuils d'exception | D2: Comparaison systeme interne / depositaire avec seuils d'exception | E2: Comparaison systeme interne / depositaire avec seuils d'exception | F2: Comparaison systeme interne / depositaire avec seuils d'exception | G2: Comparaison systeme interne / depositaire avec seuils d'exception | H2: Comparaison systeme interne / depositaire avec seuils d'exception | I2: Comparaison systeme interne / depositaire avec seuils d'exception | J2: Comparaison systeme interne / depositaire avec seuils d'exception | K2: Comparaison systeme interne / depositaire avec seuils d'exception | L2: Comparaison systeme interne / depositaire avec seuils d'exception
A4: Trade ID | B4: Sens | C4: Bond ID | D4: Date trade | E4: Nominal interne | F4: Nominal depositaire | G4: Prix interne | H4: Prix depositaire | I4: Ecart nominal | J4: Ecart prix | K4: Statut | L4: Action
A5: T01 | B5: Achat | C5: B01 | D5: 46241 | E5: 750000 | F5: 750000 | G5: 97.94 | H5: 97.94 | I5: =E5-F5 -> 0 | J5: =G5-H5 -> 0 | K5: =IF(OR(ABS(I5)>1000,ABS(J5)>0.05),"EXCEPTION","OK") -> OK | L5: =IF(K5="OK","Aucune","Verifier allocation / prix") -> Aucune
A6: T02 | B6: Achat | C6: B04 | D6: 46241 | E6: 500000 | F6: 500000 | G6: 100.39 | H6: 100.39 | I6: =E6-F6 -> 0 | J6: =G6-H6 -> 0 | K6: =IF(OR(ABS(I6)>1000,ABS(J6)>0.05),"EXCEPTION","OK") -> OK | L6: =IF(K6="OK","Aucune","Verifier allocation / prix") -> Aucune
A7: T03 | B7: Vente | C7: B02 | D7: 46242 | E7: 300000 | F7: 300000 | G7: 99.28 | H7: 99.3 | I7: =E7-F7 -> 0 | J7: =G7-H7 -> -0.02 | K7: =IF(OR(ABS(I7)>1000,ABS(J7)>0.05),"EXCEPTION","OK") -> OK | L7: =IF(K7="OK","Aucune","Verifier allocation / prix") -> Aucune
A8: T04 | B8: Achat | C8: B06 | D8: 46242 | E8: 250000 | F8: 240000 | G8: 100.91 | H8: 100.91 | I8: =E8-F8 -> 10000 | J8: =G8-H8 -> 0 | K8: =IF(OR(ABS(I8)>1000,ABS(J8)>0.05),"EXCEPTION","OK") -> EXCEPTION | L8: =IF(K8="OK","Aucune","Verifier allocation / prix") -> Verifier allocation / prix
A9: T05 | B9: Achat | C9: B03 | D9: 46243 | E9: 400000 | F9: 400000 | G9: 101.39 | H9: 101.15 | I9: =E9-F9 -> 0 | J9: =G9-H9 -> 0.24 | K9: =IF(OR(ABS(I9)>1000,ABS(J9)>0.05),"EXCEPTION","OK") -> EXCEPTION | L9: =IF(K9="OK","Aucune","Verifier allocation / prix") -> Verifier allocation / prix
A10: T06 | B10: Vente | C10: B07 | D10: 46243 | E10: 350000 | F10: 350000 | G10: 102.75 | H10: 102.75 | I10: =E10-F10 -> 0 | J10: =G10-H10 -> 0 | K10: =IF(OR(ABS(I10)>1000,ABS(J10)>0.05),"EXCEPTION","OK") -> OK | L10: =IF(K10="OK","Aucune","Verifier allocation / prix") -> Aucune
A11: T07 | B11: Achat | C11: B05 | D11: 46244 | E11: 200000 | F11: 200000 | G11: 101.29 | H11: 101.29 | I11: =E11-F11 -> 0 | J11: =G11-H11 -> 0 | K11: =IF(OR(ABS(I11)>1000,ABS(J11)>0.05),"EXCEPTION","OK") -> OK | L11: =IF(K11="OK","Aucune","Verifier allocation / prix") -> Aucune
A12: T08 | B12: Achat | C12: B08 | D12: 46244 | E12: 150000 | F12: 150000 | G12: 100.81 | H12: 100.79 | I12: =E12-F12 -> 0 | J12: =G12-H12 -> 0.02 | K12: =IF(OR(ABS(I12)>1000,ABS(J12)>0.05),"EXCEPTION","OK") -> OK | L12: =IF(K12="OK","Aucune","Verifier allocation / prix") -> Aucune

Sheet Checks
A1: Controles d'integrite du modele | B1: Controles d'integrite du modele | C1: Controles d'integrite du modele | D1: Controles d'integrite du modele | E1: Controles d'integrite du modele | F1: Controles d'integrite du modele | G1: Controles d'integrite du modele
A2: Chaque controle doit afficher OK avant utilisation | B2: Chaque controle doit afficher OK avant utilisation | C2: Chaque controle doit afficher OK avant utilisation | D2: Chaque controle doit afficher OK avant utilisation | E2: Chaque controle doit afficher OK avant utilisation | F2: Chaque controle doit afficher OK avant utilisation | G2: Chaque controle doit afficher OK avant utilisation
A4: Controle | B4: Valeur | C4: Regle | D4: Tolerance / cible | E4: Statut | F4: Localisation | G4: Commentaire
A5: Somme des poids | B5: =Portefeuille!$Q$13 -> 1 | C5: =100% -> 1 | D5: 1e-08 | E5: =IF(ABS(B5-1)<=D5,"OK","A REVOIR") -> OK | F5: Portefeuille!Q13 | G5: Allocation complete
A6: Valeur de marche positive | B6: =Portefeuille!$K$13 -> 10227860 | C6: > 0 | D6: 0 | E6: =IF(B6>D6,"OK","A REVOIR") -> OK | F6: Portefeuille!K13 | G6: Pas de portefeuille vide
A7: DV01 positive | B7: =Portefeuille!$O$13 -> 3875.1079 | C7: > 0 | D7: 0 | E7: =IF(B7>D7,"OK","A REVOIR") -> OK | F7: Portefeuille!O13 | G7: Sensibilite calculee
A8: PnL scenario Base | B8: ='Stress Tests'!$B$49 -> 0 | C8: =0 -> 0 | D8: 0.01 | E8: =IF(ABS(B8)<=D8,"OK","A REVOIR") -> OK | F8: Stress Tests!B49 | G8: Absence de choc
A9: Exceptions collateral | B9: =Collateral!$B$17 -> 1 | C9: =1 -> 1 | D9: 1 | E9: =IF(B9=D9,"OK","A REVOIR") -> OK | F9: Collateral!B17 | G9: Jeu de donnees de test
A10: Exceptions trades | B10: =COUNTIF(Reconciliation!$K$5:$K$12,"EXCEPTION") -> 2 | C10: =2 -> 2 | D10: 2 | E10: =IF(B10=D10,"OK","A REVOIR") -> OK | F10: Reconciliation!K5:K12 | G10: Jeu de donnees de test
A11: Efficacite couverture | B11: =Couverture!$B$10 -> 0.99099584 | C11: >= 95% | D11: 0.95 | E11: =IF(B11>=D11,"OK","A REVOIR") -> OK | F11: Couverture!B10 | G11: DV01 residuelle limitee
A12: Prix non positifs | B12: =COUNTIF(Portefeuille!$J$5:$J$12,"<=0") -> 0 | C12: =0 -> 0 | D12: 0 | E12: =IF(B12=D12,"OK","A REVOIR") -> OK | F12: Portefeuille!J5:J12 | G12: Controle de valorisation
A13: Stress detail = synthese | B13: =SUM('Stress Tests'!$K$13:$K$20)-'Stress Tests'!$B$50 -> 0 | C13: =0 -> 0 | D13: 0.01 | E13: =IF(ABS(B13)<=D13,"OK","A REVOIR") -> OK | F13: Stress Tests | G13: Rapprochement du pire scenario
A16: STATUT GLOBAL | B16: =IF(COUNTIF(E5:E13,"<>OK")=0,"OK","A REVOIR") -> OK
A17: Nombre d'erreurs | B17: =COUNTIF(E5:E13,"<>OK") -> 0

Sheet Sources
A1: Sources, conventions et limites | B1: Sources, conventions et limites | C1: Sources, conventions et limites | D1: Sources, conventions et limites | E1: Sources, conventions et limites | F1: Sources, conventions et limites
A2: Tracer les hypotheses et distinguer donnees officielles / donnees illustratives | B2: Tracer les hypotheses et distinguer donnees officielles / donnees illustratives | C2: Tracer les hypotheses et distinguer donnees officielles / donnees illustratives | D2: Tracer les hypotheses et distinguer donnees officielles / donnees illustratives | E2: Tracer les hypotheses et distinguer donnees officielles / donnees illustratives | F2: Tracer les hypotheses et distinguer donnees officielles / donnees illustratives
A4: ID | B4: Element | C4: Nature | D4: Source / URL | E4: Utilisation | F4: Limite
A5: S1 | B5: Offre de stage | C5: Source primaire | D5: upload/sansolongchamp.pdf | E5: Ciblage des livrables | F5: Document fourni par l'utilisatrice
A6: S2 | B6: Courbes de taux zone euro | C6: Source officielle | D6: https://www.ecb.europa.eu/stats/financial_markets_and_interest_rates/euro_area_yield_curves/html/index.en.html | E6: Definition et lecture de la courbe | F6: Valeurs du projet illustratives
A7: S3 | B7: Methodologie courbe BCE | C7: Source officielle | D7: https://www.ecb.europa.eu/stats/financial_markets_and_interest_rates/euro_area_yield_curves/html/technical_notes.pdf | E7: Actualisation des flux / structure par terme | F7: Simplification : coupons annuels
A8: S4 | B8: Gestion du collateral OTC | C8: Source professionnelle | D8: https://www.isda.org/collateral-management-sop/ | E8: Appels de marge et reconciliation | F8: CSA et regles juridiques non modelises
A9: S5 | B9: Stress de taux et sensibilites | C9: Source officielle | D9: https://www.bis.org/bcbs/publ/d578.pdf | E9: Scenarios paralleles / non paralleles | F9: Chocs pedagogiques, pas reglementaires
A10: S6 | B10: Portefeuille et prix | C10: Illustratif | D10: Genere pour ce projet | E10: Demontrer les calculs et controles | F10: Aucun instrument reel / aucune recommandation
A11: S7 | B11: DV01 future | C11: Hypothese editable | D11: 85 EUR/pb par contrat | E11: Illustrer la couverture | F11: Depend du contrat et du CTD

Sheet Guide
A1: Guide d'utilisation et presentation en entretien | B1: Guide d'utilisation et presentation en entretien | C1: Guide d'utilisation et presentation en entretien | D1: Guide d'utilisation et presentation en entretien | E1: Guide d'utilisation et presentation en entretien | F1: Guide d'utilisation et presentation en entretien | G1: Guide d'utilisation et presentation en entretien | H1: Guide d'utilisation et presentation en entretien
A2: Projet realise par Sofia Kammoune - MBA Trading & Finance de Marche | B2: Projet realise par Sofia Kammoune - MBA Trading & Finance de Marche | C2: Projet realise par Sofia Kammoune - MBA Trading & Finance de Marche | D2: Projet realise par Sofia Kammoune - MBA Trading & Finance de Marche | E2: Projet realise par Sofia Kammoune - MBA Trading & Finance de Marche | F2: Projet realise par Sofia Kammoune - MBA Trading & Finance de Marche | G2: Projet realise par Sofia Kammoune - MBA Trading & Finance de Marche | H2: Projet realise par Sofia Kammoune - MBA Trading & Finance de Marche
A4: 1. Mode d'emploi | B4: 1. Mode d'emploi | C4: 1. Mode d'emploi | D4: 1. Mode d'emploi | E4: 1. Mode d'emploi | F4: 1. Mode d'emploi | G4: 1. Mode d'emploi | H4: 1. Mode d'emploi
A5: 1) Modifier uniquement les cellules bleues ou jaunes : positions, YTM, courbe, scenarios et seuils.
A6: 2) Verifier le statut global dans Dashboard et dans Checks avant toute interpretation.
A7: 3) Lire la DV01 comme la variation approximative de valeur pour 1 point de base de taux.
A8: 4) Comparer les stress tests puis ajuster la couverture indicative dans l'onglet Couverture.
A9: 5) Examiner les exceptions dans Collateral et Reconciliation comme un flux Middle Office.
A11: 2. Correspondance avec l'offre Sanso Longchamp | B11: 2. Correspondance avec l'offre Sanso Longchamp | C11: 2. Correspondance avec l'offre Sanso Longchamp | D11: 2. Correspondance avec l'offre Sanso Longchamp | E11: 2. Correspondance avec l'offre Sanso Longchamp | F11: 2. Correspondance avec l'offre Sanso Longchamp | G11: 2. Correspondance avec l'offre Sanso Longchamp | H11: 2. Correspondance avec l'offre Sanso Longchamp
A12: Mission de l'offre | E12: Preuve dans le projet
A13: Suivi de portefeuilles obligataires | E13: Valorisation, poids, rendement et sensibilites
A14: Collatéral / appels de marge | E14: Exposition, seuil, MTA, appel et exception
A15: Rapprochement des trades | E15: Comparaison interne / depositaire et actions
A16: Modelisation et sensibilites | E16: Cashflows, duration, convexite, DV01 et stress
A17: Outils internes de gestion | E17: Dashboard Excel + reproduction Python
A19: 3. Pitch de 40 secondes | B19: 3. Pitch de 40 secondes | C19: 3. Pitch de 40 secondes | D19: 3. Pitch de 40 secondes | E19: 3. Pitch de 40 secondes | F19: 3. Pitch de 40 secondes | G19: 3. Pitch de 40 secondes | H19: 3. Pitch de 40 secondes
A20: Cet outil de suivi obligataire relie valorisation, risques et controle operationnel. Le portefeuille est calcule a partir des flux, puis j'analyse duration, convexite et DV01 sous plusieurs chocs de taux et de spreads. On ajoute une couverture indicative, un module d'appels de marge et un rapprochement interne-depositaire. Le fichier Excel reste entierement auditable et le script Python reproduit les principaux calculs. | B20: J'ai construit un outil de suivi obligataire qui relie valorisation, risques et controle operationnel. Le portefeuille est calcule a partir des flux, puis j'analyse duration, convexite et DV01 sous plusieurs chocs de taux et de spreads. J'ai ajoute une couverture indicative, un module d'appels de marge et un rapprochement interne-depositaire. Le fichier Excel reste entierement auditable et le script Python reproduit les principaux calculs. | C20: J'ai construit un outil de suivi obligataire qui relie valorisation, risques et controle operationnel. Le portefeuille est calcule a partir des flux, puis j'analyse duration, convexite et DV01 sous plusieurs chocs de taux et de spreads. J'ai ajoute une couverture indicative, un module d'appels de marge et un rapprochement interne-depositaire. Le fichier Excel reste entierement auditable et le script Python reproduit les principaux calculs. | D20: J'ai construit un outil de suivi obligataire qui relie valorisation, risques et controle operationnel. Le portefeuille est calcule a partir des flux, puis j'analyse duration, convexite et DV01 sous plusieurs chocs de taux et de spreads. J'ai ajoute une couverture indicative, un module d'appels de marge et un rapprochement interne-depositaire. Le fichier Excel reste entierement auditable et le script Python reproduit les principaux calculs. | E20: J'ai construit un outil de suivi obligataire qui relie valorisation, risques et controle operationnel. Le portefeuille est calcule a partir des flux, puis j'analyse duration, convexite et DV01 sous plusieurs chocs de taux et de spreads. J'ai ajoute une couverture indicative, un module d'appels de marge et un rapprochement interne-depositaire. Le fichier Excel reste entierement auditable et le script Python reproduit les principaux calculs. | F20: J'ai construit un outil de suivi obligataire qui relie valorisation, risques et controle operationnel. Le portefeuille est calcule a partir des flux, puis j'analyse duration, convexite et DV01 sous plusieurs chocs de taux et de spreads. J'ai ajoute une couverture indicative, un module d'appels de marge et un rapprochement interne-depositaire. Le fichier Excel reste entierement auditable et le script Python reproduit les principaux calculs. | G20: J'ai construit un outil de suivi obligataire qui relie valorisation, risques et controle operationnel. Le portefeuille est calcule a partir des flux, puis j'analyse duration, convexite et DV01 sous plusieurs chocs de taux et de spreads. J'ai ajoute une couverture indicative, un module d'appels de marge et un rapprochement interne-depositaire. Le fichier Excel reste entierement auditable et le script Python reproduit les principaux calculs. | H20: J'ai construit un outil de suivi obligataire qui relie valorisation, risques et controle operationnel. Le portefeuille est calcule a partir des flux, puis j'analyse duration, convexite et DV01 sous plusieurs chocs de taux et de spreads. J'ai ajoute une couverture indicative, un module d'appels de marge et un rapprochement interne-depositaire. Le fichier Excel reste entierement auditable et le script Python reproduit les principaux calculs.
A21: J'ai construit un outil de suivi obligataire qui relie valorisation, risques et controle operationnel. Le portefeuille est calcule a partir des flux, puis j'analyse duration, convexite et DV01 sous plusieurs chocs de taux et de spreads. J'ai ajoute une couverture indicative, un module d'appels de marge et un rapprochement interne-depositaire. Le fichier Excel reste entierement auditable et le script Python reproduit les principaux calculs. | B21: J'ai construit un outil de suivi obligataire qui relie valorisation, risques et controle operationnel. Le portefeuille est calcule a partir des flux, puis j'analyse duration, convexite et DV01 sous plusieurs chocs de taux et de spreads. J'ai ajoute une couverture indicative, un module d'appels de marge et un rapprochement interne-depositaire. Le fichier Excel reste entierement auditable et le script Python reproduit les principaux calculs. | C21: J'ai construit un outil de suivi obligataire qui relie valorisation, risques et controle operationnel. Le portefeuille est calcule a partir des flux, puis j'analyse duration, convexite et DV01 sous plusieurs chocs de taux et de spreads. J'ai ajoute une couverture indicative, un module d'appels de marge et un rapprochement interne-depositaire. Le fichier Excel reste entierement auditable et le script Python reproduit les principaux calculs. | D21: J'ai construit un outil de suivi obligataire qui relie valorisation, risques et controle operationnel. Le portefeuille est calcule a partir des flux, puis j'analyse duration, convexite et DV01 sous plusieurs chocs de taux et de spreads. J'ai ajoute une couverture indicative, un module d'appels de marge et un rapprochement interne-depositaire. Le fichier Excel reste entierement auditable et le script Python reproduit les principaux calculs. | E21: J'ai construit un outil de suivi obligataire qui relie valorisation, risques et controle operationnel. Le portefeuille est calcule a partir des flux, puis j'analyse duration, convexite et DV01 sous plusieurs chocs de taux et de spreads. J'ai ajoute une couverture indicative, un module d'appels de marge et un rapprochement interne-depositaire. Le fichier Excel reste entierement auditable et le script Python reproduit les principaux calculs. | F21: J'ai construit un outil de suivi obligataire qui relie valorisation, risques et controle operationnel. Le portefeuille est calcule a partir des flux, puis j'analyse duration, convexite et DV01 sous plusieurs chocs de taux et de spreads. J'ai ajoute une couverture indicative, un module d'appels de marge et un rapprochement interne-depositaire. Le fichier Excel reste entierement auditable et le script Python reproduit les principaux calculs. | G21: J'ai construit un outil de suivi obligataire qui relie valorisation, risques et controle operationnel. Le portefeuille est calcule a partir des flux, puis j'analyse duration, convexite et DV01 sous plusieurs chocs de taux et de spreads. J'ai ajoute une couverture indicative, un module d'appels de marge et un rapprochement interne-depositaire. Le fichier Excel reste entierement auditable et le script Python reproduit les principaux calculs. | H21: J'ai construit un outil de suivi obligataire qui relie valorisation, risques et controle operationnel. Le portefeuille est calcule a partir des flux, puis j'analyse duration, convexite et DV01 sous plusieurs chocs de taux et de spreads. J'ai ajoute une couverture indicative, un module d'appels de marge et un rapprochement interne-depositaire. Le fichier Excel reste entierement auditable et le script Python reproduit les principaux calculs.
A22: J'ai construit un outil de suivi obligataire qui relie valorisation, risques et controle operationnel. Le portefeuille est calcule a partir des flux, puis j'analyse duration, convexite et DV01 sous plusieurs chocs de taux et de spreads. J'ai ajoute une couverture indicative, un module d'appels de marge et un rapprochement interne-depositaire. Le fichier Excel reste entierement auditable et le script Python reproduit les principaux calculs. | B22: J'ai construit un outil de suivi obligataire qui relie valorisation, risques et controle operationnel. Le portefeuille est calcule a partir des flux, puis j'analyse duration, convexite et DV01 sous plusieurs chocs de taux et de spreads. J'ai ajoute une couverture indicative, un module d'appels de marge et un rapprochement interne-depositaire. Le fichier Excel reste entierement auditable et le script Python reproduit les principaux calculs. | C22: J'ai construit un outil de suivi obligataire qui relie valorisation, risques et controle operationnel. Le portefeuille est calcule a partir des flux, puis j'analyse duration, convexite et DV01 sous plusieurs chocs de taux et de spreads. J'ai ajoute une couverture indicative, un module d'appels de marge et un rapprochement interne-depositaire. Le fichier Excel reste entierement auditable et le script Python reproduit les principaux calculs. | D22: J'ai construit un outil de suivi obligataire qui relie valorisation, risques et controle operationnel. Le portefeuille est calcule a partir des flux, puis j'analyse duration, convexite et DV01 sous plusieurs chocs de taux et de spreads. J'ai ajoute une couverture indicative, un module d'appels de marge et un rapprochement interne-depositaire. Le fichier Excel reste entierement auditable et le script Python reproduit les principaux calculs. | E22: J'ai construit un outil de suivi obligataire qui relie valorisation, risques et controle operationnel. Le portefeuille est calcule a partir des flux, puis j'analyse duration, convexite et DV01 sous plusieurs chocs de taux et de spreads. J'ai ajoute une couverture indicative, un module d'appels de marge et un rapprochement interne-depositaire. Le fichier Excel reste entierement auditable et le script Python reproduit les principaux calculs. | F22: J'ai construit un outil de suivi obligataire qui relie valorisation, risques et controle operationnel. Le portefeuille est calcule a partir des flux, puis j'analyse duration, convexite et DV01 sous plusieurs chocs de taux et de spreads. J'ai ajoute une couverture indicative, un module d'appels de marge et un rapprochement interne-depositaire. Le fichier Excel reste entierement auditable et le script Python reproduit les principaux calculs. | G22: J'ai construit un outil de suivi obligataire qui relie valorisation, risques et controle operationnel. Le portefeuille est calcule a partir des flux, puis j'analyse duration, convexite et DV01 sous plusieurs chocs de taux et de spreads. J'ai ajoute une couverture indicative, un module d'appels de marge et un rapprochement interne-depositaire. Le fichier Excel reste entierement auditable et le script Python reproduit les principaux calculs. | H22: J'ai construit un outil de suivi obligataire qui relie valorisation, risques et controle operationnel. Le portefeuille est calcule a partir des flux, puis j'analyse duration, convexite et DV01 sous plusieurs chocs de taux et de spreads. J'ai ajoute une couverture indicative, un module d'appels de marge et un rapprochement interne-depositaire. Le fichier Excel reste entierement auditable et le script Python reproduit les principaux calculs.
A23: J'ai construit un outil de suivi obligataire qui relie valorisation, risques et controle operationnel. Le portefeuille est calcule a partir des flux, puis j'analyse duration, convexite et DV01 sous plusieurs chocs de taux et de spreads. J'ai ajoute une couverture indicative, un module d'appels de marge et un rapprochement interne-depositaire. Le fichier Excel reste entierement auditable et le script Python reproduit les principaux calculs. | B23: J'ai construit un outil de suivi obligataire qui relie valorisation, risques et controle operationnel. Le portefeuille est calcule a partir des flux, puis j'analyse duration, convexite et DV01 sous plusieurs chocs de taux et de spreads. J'ai ajoute une couverture indicative, un module d'appels de marge et un rapprochement interne-depositaire. Le fichier Excel reste entierement auditable et le script Python reproduit les principaux calculs. | C23: J'ai construit un outil de suivi obligataire qui relie valorisation, risques et controle operationnel. Le portefeuille est calcule a partir des flux, puis j'analyse duration, convexite et DV01 sous plusieurs chocs de taux et de spreads. J'ai ajoute une couverture indicative, un module d'appels de marge et un rapprochement interne-depositaire. Le fichier Excel reste entierement auditable et le script Python reproduit les principaux calculs. | D23: J'ai construit un outil de suivi obligataire qui relie valorisation, risques et controle operationnel. Le portefeuille est calcule a partir des flux, puis j'analyse duration, convexite et DV01 sous plusieurs chocs de taux et de spreads. J'ai ajoute une couverture indicative, un module d'appels de marge et un rapprochement interne-depositaire. Le fichier Excel reste entierement auditable et le script Python reproduit les principaux calculs. | E23: J'ai construit un outil de suivi obligataire qui relie valorisation, risques et controle operationnel. Le portefeuille est calcule a partir des flux, puis j'analyse duration, convexite et DV01 sous plusieurs chocs de taux et de spreads. J'ai ajoute une couverture indicative, un module d'appels de marge et un rapprochement interne-depositaire. Le fichier Excel reste entierement auditable et le script Python reproduit les principaux calculs. | F23: J'ai construit un outil de suivi obligataire qui relie valorisation, risques et controle operationnel. Le portefeuille est calcule a partir des flux, puis j'analyse duration, convexite et DV01 sous plusieurs chocs de taux et de spreads. J'ai ajoute une couverture indicative, un module d'appels de marge et un rapprochement interne-depositaire. Le fichier Excel reste entierement auditable et le script Python reproduit les principaux calculs. | G23: J'ai construit un outil de suivi obligataire qui relie valorisation, risques et controle operationnel. Le portefeuille est calcule a partir des flux, puis j'analyse duration, convexite et DV01 sous plusieurs chocs de taux et de spreads. J'ai ajoute une couverture indicative, un module d'appels de marge et un rapprochement interne-depositaire. Le fichier Excel reste entierement auditable et le script Python reproduit les principaux calculs. | H23: J'ai construit un outil de suivi obligataire qui relie valorisation, risques et controle operationnel. Le portefeuille est calcule a partir des flux, puis j'analyse duration, convexite et DV01 sous plusieurs chocs de taux et de spreads. J'ai ajoute une couverture indicative, un module d'appels de marge et un rapprochement interne-depositaire. Le fichier Excel reste entierement auditable et le script Python reproduit les principaux calculs.
